<stg><name>load_input_wide</name>


<trans_list>

<trans id="98" from="1" to="2">
<condition id="-1">
<or_exp><and_exp></and_exp></or_exp>
</condition>
</trans>

<trans id="99" from="2" to="3">
<condition id="-1">
<or_exp><and_exp></and_exp></or_exp>
</condition>
</trans>

<trans id="100" from="3" to="4">
<condition id="-1">
<or_exp><and_exp></and_exp></or_exp>
</condition>
</trans>

<trans id="101" from="4" to="5">
<condition id="-1">
<or_exp><and_exp></and_exp></or_exp>
</condition>
</trans>

<trans id="102" from="5" to="6">
<condition id="-1">
<or_exp><and_exp></and_exp></or_exp>
</condition>
</trans>

<trans id="103" from="6" to="7">
<condition id="-1">
<or_exp><and_exp></and_exp></or_exp>
</condition>
</trans>

<trans id="104" from="7" to="8">
<condition id="-1">
<or_exp><and_exp></and_exp></or_exp>
</condition>
</trans>

<trans id="105" from="8" to="9">
<condition id="-1">
<or_exp><and_exp></and_exp></or_exp>
</condition>
</trans>

<trans id="106" from="9" to="10">
<condition id="-1">
<or_exp><and_exp></and_exp></or_exp>
</condition>
</trans>

<trans id="107" from="10" to="11">
<condition id="-1">
<or_exp><and_exp></and_exp></or_exp>
</condition>
</trans>

<trans id="108" from="11" to="12">
<condition id="-1">
<or_exp><and_exp></and_exp></or_exp>
</condition>
</trans>

<trans id="109" from="12" to="13">
<condition id="-1">
<or_exp><and_exp></and_exp></or_exp>
</condition>
</trans>
</trans_list>



<state_list>

<state id="1" st_id="2">

<operation id="16" st_id="1" stage="1" lat="1">
<core>NULL</core>
<MemPortIdVec></MemPortIdVec>
<condition id="-1">
<or_exp><and_exp></and_exp></or_exp>
</condition>

<Node id="4" bw="12" op_0_bw="32">
<![CDATA[
entry:0 %i1 = alloca i32 1

]]></Node>
<StgValue><ssdm name="i1"/></StgValue>
</operation>

<operation id="17" st_id="1" stage="1" lat="1">
<core>NULL</core>
<MemPortIdVec></MemPortIdVec>
<condition id="-1">
<or_exp><and_exp></and_exp></or_exp>
</condition>

<Node id="5" bw="0" op_0_bw="0" op_1_bw="512" op_2_bw="0" op_3_bw="32" op_4_bw="32" op_5_bw="0" op_6_bw="32" op_7_bw="32" op_8_bw="0" op_9_bw="0" op_10_bw="0" op_11_bw="32" op_12_bw="32" op_13_bw="32" op_14_bw="32" op_15_bw="0" op_16_bw="0" op_17_bw="32" op_18_bw="32" op_19_bw="32">
<![CDATA[
entry:1 %specinterface_ln0 = specinterface void @_ssdm_op_SpecInterface, i512 %s_in, void @empty_18, i32 0, i32 0, void @empty_12, i32 0, i32 0, void @empty_12, void @empty_12, void @empty_12, i32 0, i32 0, i32 0, i32 0, void @empty_12, void @empty_12, i32 4294967295, i32 0, i32 0

]]></Node>
<StgValue><ssdm name="specinterface_ln0"/></StgValue>
</operation>

<operation id="18" st_id="1" stage="1" lat="1">
<core>NULL</core>
<MemPortIdVec></MemPortIdVec>
<condition id="-1">
<or_exp><and_exp></and_exp></or_exp>
</condition>

<Node id="6" bw="0" op_0_bw="0" op_1_bw="512" op_2_bw="0" op_3_bw="32" op_4_bw="32" op_5_bw="0" op_6_bw="32" op_7_bw="32" op_8_bw="0" op_9_bw="0" op_10_bw="0" op_11_bw="32" op_12_bw="32" op_13_bw="32" op_14_bw="32" op_15_bw="0" op_16_bw="0" op_17_bw="32" op_18_bw="32" op_19_bw="32">
<![CDATA[
entry:2 %specinterface_ln0 = specinterface void @_ssdm_op_SpecInterface, i512 %s_in, void @empty_18, i32 0, i32 0, void @empty_12, i32 0, i32 0, void @empty_12, void @empty_12, void @empty_12, i32 0, i32 0, i32 0, i32 0, void @empty_12, void @empty_12, i32 4294967295, i32 0, i32 0

]]></Node>
<StgValue><ssdm name="specinterface_ln0"/></StgValue>
</operation>

<operation id="19" st_id="1" stage="1" lat="1">
<core>NULL</core>
<MemPortIdVec></MemPortIdVec>
<condition id="-1">
<or_exp><and_exp></and_exp></or_exp>
</condition>

<Node id="7" bw="0" op_0_bw="0" op_1_bw="512" op_2_bw="0" op_3_bw="32" op_4_bw="32" op_5_bw="0" op_6_bw="32" op_7_bw="32" op_8_bw="0" op_9_bw="0" op_10_bw="0" op_11_bw="32" op_12_bw="32" op_13_bw="32" op_14_bw="32" op_15_bw="0" op_16_bw="0" op_17_bw="32" op_18_bw="32" op_19_bw="32">
<![CDATA[
entry:3 %specinterface_ln0 = specinterface void @_ssdm_op_SpecInterface, i512 %s_in, void @empty_18, i32 0, i32 0, void @empty_12, i32 0, i32 0, void @empty_12, void @empty_12, void @empty_12, i32 0, i32 0, i32 0, i32 0, void @empty_12, void @empty_12, i32 4294967295, i32 0, i32 0

]]></Node>
<StgValue><ssdm name="specinterface_ln0"/></StgValue>
</operation>

<operation id="20" st_id="1" stage="1" lat="1">
<core>NULL</core>
<MemPortIdVec></MemPortIdVec>
<condition id="-1">
<or_exp><and_exp></and_exp></or_exp>
</condition>

<Node id="8" bw="0" op_0_bw="0" op_1_bw="512" op_2_bw="0" op_3_bw="32" op_4_bw="32" op_5_bw="0" op_6_bw="32" op_7_bw="32" op_8_bw="0" op_9_bw="0" op_10_bw="0" op_11_bw="32" op_12_bw="32" op_13_bw="32" op_14_bw="32" op_15_bw="0" op_16_bw="0" op_17_bw="32" op_18_bw="32" op_19_bw="32">
<![CDATA[
entry:4 %specinterface_ln0 = specinterface void @_ssdm_op_SpecInterface, i512 %s_in, void @empty_18, i32 0, i32 0, void @empty_12, i32 0, i32 0, void @empty_12, void @empty_12, void @empty_12, i32 0, i32 0, i32 0, i32 0, void @empty_12, void @empty_12, i32 4294967295, i32 0, i32 0

]]></Node>
<StgValue><ssdm name="specinterface_ln0"/></StgValue>
</operation>

<operation id="21" st_id="1" stage="1" lat="1">
<core>NULL</core>
<MemPortIdVec></MemPortIdVec>
<condition id="-1">
<or_exp><and_exp></and_exp></or_exp>
</condition>

<Node id="9" bw="0" op_0_bw="0" op_1_bw="512" op_2_bw="0" op_3_bw="32" op_4_bw="32" op_5_bw="0" op_6_bw="32" op_7_bw="32" op_8_bw="0" op_9_bw="0" op_10_bw="0" op_11_bw="32" op_12_bw="32" op_13_bw="32" op_14_bw="32" op_15_bw="0" op_16_bw="0" op_17_bw="32" op_18_bw="32" op_19_bw="32">
<![CDATA[
entry:5 %specinterface_ln0 = specinterface void @_ssdm_op_SpecInterface, i512 %gmem0, void @empty_13, i32 0, i32 0, void @empty_12, i32 3, i32 4096, void @empty_11, void @empty_10, void @empty_12, i32 16, i32 16, i32 16, i32 16, void @empty_12, void @empty_12, i32 4294967295, i32 0, i32 0

]]></Node>
<StgValue><ssdm name="specinterface_ln0"/></StgValue>
</operation>

<operation id="22" st_id="1" stage="1" lat="1">
<core>NULL</core>
<MemPortIdVec></MemPortIdVec>
<condition id="-1">
<or_exp><and_exp></and_exp></or_exp>
</condition>

<Node id="10" bw="64" op_0_bw="64" op_1_bw="64">
<![CDATA[
entry:6 %in_read = read i64 @_ssdm_op_Read.ap_auto.i64, i64 %in_r

]]></Node>
<StgValue><ssdm name="in_read"/></StgValue>
</operation>

<operation id="23" st_id="1" stage="1" lat="1">
<core>NULL</core>
<MemPortIdVec></MemPortIdVec>
<condition id="-1">
<or_exp><and_exp></and_exp></or_exp>
</condition>

<Node id="11" bw="0" op_0_bw="12" op_1_bw="12">
<![CDATA[
entry:7 %store_ln0 = store i12 0, i12 %i1

]]></Node>
<StgValue><ssdm name="store_ln0"/></StgValue>
</operation>

<operation id="24" st_id="1" stage="1" lat="1">
<core>NULL</core>
<MemPortIdVec></MemPortIdVec>
<condition id="-1">
<or_exp><and_exp></and_exp></or_exp>
</condition>

<Node id="12" bw="0" op_0_bw="0">
<![CDATA[
entry:8 %br_ln321 = br void %new.header

]]></Node>
<StgValue><ssdm name="br_ln321"/></StgValue>
</operation>

<operation id="25" st_id="1" stage="1" lat="1">
<core>NULL</core>
<MemPortIdVec></MemPortIdVec>
<condition id="-1">
<or_exp><and_exp></and_exp></or_exp>
</condition>

<Node id="14" bw="1" op_0_bw="1" op_1_bw="0" op_2_bw="1" op_3_bw="0">
<![CDATA[
new.header:0 %first_iter_0 = phi i1 1, void %entry, i1 0, void %VITIS_LOOP_333_1.split.i

]]></Node>
<StgValue><ssdm name="first_iter_0"/></StgValue>
</operation>

<operation id="26" st_id="1" stage="1" lat="1">
<core>NULL</core>
<MemPortIdVec></MemPortIdVec>
<condition id="-1">
<or_exp><and_exp></and_exp></or_exp>
</condition>

<Node id="18" bw="0" op_0_bw="1" op_1_bw="0" op_2_bw="0">
<![CDATA[
new.header:4 %br_ln0 = br i1 %first_iter_0, void %VITIS_LOOP_333_1.split.i, void %for.first.iter.VITIS_LOOP_333_1.split.i

]]></Node>
<StgValue><ssdm name="br_ln0"/></StgValue>
</operation>

<operation id="27" st_id="1" stage="1" lat="1">
<core>NULL</core>
<MemPortIdVec></MemPortIdVec>
<condition id="-1">
<or_exp><and_exp></and_exp></or_exp>
</condition>

<Node id="23" bw="12" op_0_bw="12" op_1_bw="0">
<![CDATA[
VITIS_LOOP_333_1.split.i:0 %i1_load = load i12 %i1

]]></Node>
<StgValue><ssdm name="i1_load"/></StgValue>
</operation>

<operation id="28" st_id="1" stage="1" lat="1">
<core>Adder</core>
<MemPortIdVec></MemPortIdVec>
<condition id="-1">
<or_exp><and_exp></and_exp></or_exp>
</condition>

<Node id="47" bw="12" op_0_bw="12" op_1_bw="12">
<![CDATA[
VITIS_LOOP_333_1.split.i:24 %i = add i12 %i1_load, i12 1

]]></Node>
<StgValue><ssdm name="i"/></StgValue>
</operation>

<operation id="29" st_id="1" stage="1" lat="1">
<core>Cmp</core>
<MemPortIdVec></MemPortIdVec>
<condition id="-1">
<or_exp><and_exp></and_exp></or_exp>
</condition>

<Node id="48" bw="1" op_0_bw="12" op_1_bw="12">
<![CDATA[
VITIS_LOOP_333_1.split.i:25 %icmp_ln321 = icmp_eq  i12 %i1_load, i12 4095

]]></Node>
<StgValue><ssdm name="icmp_ln321"/></StgValue>
</operation>

<operation id="30" st_id="1" stage="1" lat="1">
<core>NULL</core>
<MemPortIdVec></MemPortIdVec>
<condition id="-1">
<or_exp><and_exp></and_exp></or_exp>
</condition>

<Node id="49" bw="0" op_0_bw="12" op_1_bw="12" op_2_bw="0" op_3_bw="0">
<![CDATA[
VITIS_LOOP_333_1.split.i:26 %store_ln321 = store i12 %i, i12 %i1

]]></Node>
<StgValue><ssdm name="store_ln321"/></StgValue>
</operation>

<operation id="31" st_id="1" stage="1" lat="1">
<core>NULL</core>
<MemPortIdVec></MemPortIdVec>
<condition id="-1">
<or_exp><and_exp></and_exp></or_exp>
</condition>

<Node id="50" bw="0" op_0_bw="1" op_1_bw="0" op_2_bw="0">
<![CDATA[
VITIS_LOOP_333_1.split.i:27 %br_ln321 = br i1 %icmp_ln321, void %new.header, void %load_input_wide.exit

]]></Node>
<StgValue><ssdm name="br_ln321"/></StgValue>
</operation>
</state>

<state id="2" st_id="3">

<operation id="32" st_id="2" stage="1" lat="1">
<core>NULL</core>
<MemPortIdVec></MemPortIdVec>
<condition id="-1">
<or_exp><and_exp></and_exp></or_exp>
</condition>

<Node id="15" bw="58" op_0_bw="58" op_1_bw="64" op_2_bw="32" op_3_bw="32">
<![CDATA[
new.header:1 %trunc_ln = partselect i58 @_ssdm_op_PartSelect.i58.i64.i32.i32, i64 %in_read, i32 6, i32 63

]]></Node>
<StgValue><ssdm name="trunc_ln"/></StgValue>
</operation>

<operation id="33" st_id="2" stage="1" lat="1">
<core>NULL</core>
<MemPortIdVec></MemPortIdVec>
<condition id="-1">
<or_exp><and_exp></and_exp></or_exp>
</condition>

<Node id="16" bw="64" op_0_bw="58">
<![CDATA[
new.header:2 %sext_ln321 = sext i58 %trunc_ln

]]></Node>
<StgValue><ssdm name="sext_ln321"/></StgValue>
</operation>

<operation id="34" st_id="2" stage="1" lat="1">
<core>NULL</core>
<MemPortIdVec></MemPortIdVec>
<condition id="-1">
<or_exp><and_exp></and_exp></or_exp>
</condition>

<Node id="17" bw="64" op_0_bw="64" op_1_bw="64">
<![CDATA[
new.header:3 %gmem0_addr = getelementptr i512 %gmem0, i64 %sext_ln321

]]></Node>
<StgValue><ssdm name="gmem0_addr"/></StgValue>
</operation>

<operation id="35" st_id="2" stage="10" lat="10">
<core>m_axi</core>
<MemPortIdVec>0 </MemPortIdVec>
<condition id="-1">
<or_exp><and_exp><literal name="first_iter_0" val="1"/>
</and_exp></or_exp>
</condition>

<Node id="20" bw="1" op_0_bw="1" op_1_bw="512" op_2_bw="64">
<![CDATA[
for.first.iter.VITIS_LOOP_333_1.split.i:0 %empty = readreq i1 @_ssdm_op_ReadReq.m_axi.p1i512, i64 %gmem0_addr, i64 4096

]]></Node>
<StgValue><ssdm name="empty"/></StgValue>
</operation>
</state>

<state id="3" st_id="4">

<operation id="36" st_id="3" stage="9" lat="10">
<core>m_axi</core>
<MemPortIdVec>0 </MemPortIdVec>
<condition id="-1">
<or_exp><and_exp><literal name="first_iter_0" val="1"/>
</and_exp></or_exp>
</condition>

<Node id="20" bw="1" op_0_bw="1" op_1_bw="512" op_2_bw="64">
<![CDATA[
for.first.iter.VITIS_LOOP_333_1.split.i:0 %empty = readreq i1 @_ssdm_op_ReadReq.m_axi.p1i512, i64 %gmem0_addr, i64 4096

]]></Node>
<StgValue><ssdm name="empty"/></StgValue>
</operation>
</state>

<state id="4" st_id="5">

<operation id="37" st_id="4" stage="8" lat="10">
<core>m_axi</core>
<MemPortIdVec>0 </MemPortIdVec>
<condition id="-1">
<or_exp><and_exp><literal name="first_iter_0" val="1"/>
</and_exp></or_exp>
</condition>

<Node id="20" bw="1" op_0_bw="1" op_1_bw="512" op_2_bw="64">
<![CDATA[
for.first.iter.VITIS_LOOP_333_1.split.i:0 %empty = readreq i1 @_ssdm_op_ReadReq.m_axi.p1i512, i64 %gmem0_addr, i64 4096

]]></Node>
<StgValue><ssdm name="empty"/></StgValue>
</operation>
</state>

<state id="5" st_id="6">

<operation id="38" st_id="5" stage="7" lat="10">
<core>m_axi</core>
<MemPortIdVec>0 </MemPortIdVec>
<condition id="-1">
<or_exp><and_exp><literal name="first_iter_0" val="1"/>
</and_exp></or_exp>
</condition>

<Node id="20" bw="1" op_0_bw="1" op_1_bw="512" op_2_bw="64">
<![CDATA[
for.first.iter.VITIS_LOOP_333_1.split.i:0 %empty = readreq i1 @_ssdm_op_ReadReq.m_axi.p1i512, i64 %gmem0_addr, i64 4096

]]></Node>
<StgValue><ssdm name="empty"/></StgValue>
</operation>
</state>

<state id="6" st_id="7">

<operation id="39" st_id="6" stage="6" lat="10">
<core>m_axi</core>
<MemPortIdVec>0 </MemPortIdVec>
<condition id="-1">
<or_exp><and_exp><literal name="first_iter_0" val="1"/>
</and_exp></or_exp>
</condition>

<Node id="20" bw="1" op_0_bw="1" op_1_bw="512" op_2_bw="64">
<![CDATA[
for.first.iter.VITIS_LOOP_333_1.split.i:0 %empty = readreq i1 @_ssdm_op_ReadReq.m_axi.p1i512, i64 %gmem0_addr, i64 4096

]]></Node>
<StgValue><ssdm name="empty"/></StgValue>
</operation>
</state>

<state id="7" st_id="8">

<operation id="40" st_id="7" stage="5" lat="10">
<core>m_axi</core>
<MemPortIdVec>0 </MemPortIdVec>
<condition id="-1">
<or_exp><and_exp><literal name="first_iter_0" val="1"/>
</and_exp></or_exp>
</condition>

<Node id="20" bw="1" op_0_bw="1" op_1_bw="512" op_2_bw="64">
<![CDATA[
for.first.iter.VITIS_LOOP_333_1.split.i:0 %empty = readreq i1 @_ssdm_op_ReadReq.m_axi.p1i512, i64 %gmem0_addr, i64 4096

]]></Node>
<StgValue><ssdm name="empty"/></StgValue>
</operation>
</state>

<state id="8" st_id="9">

<operation id="41" st_id="8" stage="4" lat="10">
<core>m_axi</core>
<MemPortIdVec>0 </MemPortIdVec>
<condition id="-1">
<or_exp><and_exp><literal name="first_iter_0" val="1"/>
</and_exp></or_exp>
</condition>

<Node id="20" bw="1" op_0_bw="1" op_1_bw="512" op_2_bw="64">
<![CDATA[
for.first.iter.VITIS_LOOP_333_1.split.i:0 %empty = readreq i1 @_ssdm_op_ReadReq.m_axi.p1i512, i64 %gmem0_addr, i64 4096

]]></Node>
<StgValue><ssdm name="empty"/></StgValue>
</operation>
</state>

<state id="9" st_id="10">

<operation id="42" st_id="9" stage="3" lat="10">
<core>m_axi</core>
<MemPortIdVec>0 </MemPortIdVec>
<condition id="-1">
<or_exp><and_exp><literal name="first_iter_0" val="1"/>
</and_exp></or_exp>
</condition>

<Node id="20" bw="1" op_0_bw="1" op_1_bw="512" op_2_bw="64">
<![CDATA[
for.first.iter.VITIS_LOOP_333_1.split.i:0 %empty = readreq i1 @_ssdm_op_ReadReq.m_axi.p1i512, i64 %gmem0_addr, i64 4096

]]></Node>
<StgValue><ssdm name="empty"/></StgValue>
</operation>
</state>

<state id="10" st_id="11">

<operation id="43" st_id="10" stage="2" lat="10">
<core>m_axi</core>
<MemPortIdVec>0 </MemPortIdVec>
<condition id="-1">
<or_exp><and_exp><literal name="first_iter_0" val="1"/>
</and_exp></or_exp>
</condition>

<Node id="20" bw="1" op_0_bw="1" op_1_bw="512" op_2_bw="64">
<![CDATA[
for.first.iter.VITIS_LOOP_333_1.split.i:0 %empty = readreq i1 @_ssdm_op_ReadReq.m_axi.p1i512, i64 %gmem0_addr, i64 4096

]]></Node>
<StgValue><ssdm name="empty"/></StgValue>
</operation>
</state>

<state id="11" st_id="12">

<operation id="44" st_id="11" stage="1" lat="10">
<core>m_axi</core>
<MemPortIdVec>0 </MemPortIdVec>
<condition id="-1">
<or_exp><and_exp><literal name="first_iter_0" val="1"/>
</and_exp></or_exp>
</condition>

<Node id="20" bw="1" op_0_bw="1" op_1_bw="512" op_2_bw="64">
<![CDATA[
for.first.iter.VITIS_LOOP_333_1.split.i:0 %empty = readreq i1 @_ssdm_op_ReadReq.m_axi.p1i512, i64 %gmem0_addr, i64 4096

]]></Node>
<StgValue><ssdm name="empty"/></StgValue>
</operation>

<operation id="45" st_id="11" stage="1" lat="1">
<core>NULL</core>
<MemPortIdVec></MemPortIdVec>
<condition id="-1">
<or_exp><and_exp><literal name="first_iter_0" val="1"/>
</and_exp></or_exp>
</condition>

<Node id="21" bw="0" op_0_bw="0">
<![CDATA[
for.first.iter.VITIS_LOOP_333_1.split.i:1 %br_ln0 = br void %VITIS_LOOP_333_1.split.i

]]></Node>
<StgValue><ssdm name="br_ln0"/></StgValue>
</operation>
</state>

<state id="12" st_id="13">

<operation id="46" st_id="12" stage="1" lat="1">
<core>m_axi</core>
<MemPortIdVec>0 </MemPortIdVec>
<condition id="-1">
<or_exp><and_exp></and_exp></or_exp>
</condition>

<Node id="27" bw="512" op_0_bw="512" op_1_bw="512" op_2_bw="0">
<![CDATA[
VITIS_LOOP_333_1.split.i:4 %buffered_data = read i512 @_ssdm_op_Read.m_axi.p1i512, i64 %gmem0_addr

]]></Node>
<StgValue><ssdm name="buffered_data"/></StgValue>
</operation>

<operation id="47" st_id="12" stage="1" lat="1">
<core>NULL</core>
<MemPortIdVec></MemPortIdVec>
<condition id="-1">
<or_exp><and_exp></and_exp></or_exp>
</condition>

<Node id="28" bw="20" op_0_bw="512">
<![CDATA[
VITIS_LOOP_333_1.split.i:5 %trunc_ln336 = trunc i512 %buffered_data

]]></Node>
<StgValue><ssdm name="trunc_ln336"/></StgValue>
</operation>

<operation id="48" st_id="12" stage="1" lat="1">
<core>NULL</core>
<MemPortIdVec></MemPortIdVec>
<condition id="-1">
<or_exp><and_exp></and_exp></or_exp>
</condition>

<Node id="29" bw="20" op_0_bw="20" op_1_bw="512" op_2_bw="32" op_3_bw="32">
<![CDATA[
VITIS_LOOP_333_1.split.i:6 %tmp_i = partselect i20 @_ssdm_op_PartSelect.i20.i512.i32.i32, i512 %buffered_data, i32 32, i32 51

]]></Node>
<StgValue><ssdm name="tmp_i"/></StgValue>
</operation>

<operation id="49" st_id="12" stage="1" lat="1">
<core>NULL</core>
<MemPortIdVec></MemPortIdVec>
<condition id="-1">
<or_exp><and_exp></and_exp></or_exp>
</condition>

<Node id="30" bw="20" op_0_bw="20" op_1_bw="512" op_2_bw="32" op_3_bw="32">
<![CDATA[
VITIS_LOOP_333_1.split.i:7 %tmp_15_i = partselect i20 @_ssdm_op_PartSelect.i20.i512.i32.i32, i512 %buffered_data, i32 64, i32 83

]]></Node>
<StgValue><ssdm name="tmp_15_i"/></StgValue>
</operation>

<operation id="50" st_id="12" stage="1" lat="1">
<core>NULL</core>
<MemPortIdVec></MemPortIdVec>
<condition id="-1">
<or_exp><and_exp></and_exp></or_exp>
</condition>

<Node id="31" bw="20" op_0_bw="20" op_1_bw="512" op_2_bw="32" op_3_bw="32">
<![CDATA[
VITIS_LOOP_333_1.split.i:8 %tmp_16_i = partselect i20 @_ssdm_op_PartSelect.i20.i512.i32.i32, i512 %buffered_data, i32 96, i32 115

]]></Node>
<StgValue><ssdm name="tmp_16_i"/></StgValue>
</operation>

<operation id="51" st_id="12" stage="1" lat="1">
<core>NULL</core>
<MemPortIdVec></MemPortIdVec>
<condition id="-1">
<or_exp><and_exp></and_exp></or_exp>
</condition>

<Node id="32" bw="20" op_0_bw="20" op_1_bw="512" op_2_bw="32" op_3_bw="32">
<![CDATA[
VITIS_LOOP_333_1.split.i:9 %tmp_17_i = partselect i20 @_ssdm_op_PartSelect.i20.i512.i32.i32, i512 %buffered_data, i32 128, i32 147

]]></Node>
<StgValue><ssdm name="tmp_17_i"/></StgValue>
</operation>

<operation id="52" st_id="12" stage="1" lat="1">
<core>NULL</core>
<MemPortIdVec></MemPortIdVec>
<condition id="-1">
<or_exp><and_exp></and_exp></or_exp>
</condition>

<Node id="33" bw="20" op_0_bw="20" op_1_bw="512" op_2_bw="32" op_3_bw="32">
<![CDATA[
VITIS_LOOP_333_1.split.i:10 %tmp_18_i = partselect i20 @_ssdm_op_PartSelect.i20.i512.i32.i32, i512 %buffered_data, i32 160, i32 179

]]></Node>
<StgValue><ssdm name="tmp_18_i"/></StgValue>
</operation>

<operation id="53" st_id="12" stage="1" lat="1">
<core>NULL</core>
<MemPortIdVec></MemPortIdVec>
<condition id="-1">
<or_exp><and_exp></and_exp></or_exp>
</condition>

<Node id="34" bw="20" op_0_bw="20" op_1_bw="512" op_2_bw="32" op_3_bw="32">
<![CDATA[
VITIS_LOOP_333_1.split.i:11 %tmp_19_i = partselect i20 @_ssdm_op_PartSelect.i20.i512.i32.i32, i512 %buffered_data, i32 192, i32 211

]]></Node>
<StgValue><ssdm name="tmp_19_i"/></StgValue>
</operation>

<operation id="54" st_id="12" stage="1" lat="1">
<core>NULL</core>
<MemPortIdVec></MemPortIdVec>
<condition id="-1">
<or_exp><and_exp></and_exp></or_exp>
</condition>

<Node id="35" bw="20" op_0_bw="20" op_1_bw="512" op_2_bw="32" op_3_bw="32">
<![CDATA[
VITIS_LOOP_333_1.split.i:12 %tmp_20_i = partselect i20 @_ssdm_op_PartSelect.i20.i512.i32.i32, i512 %buffered_data, i32 224, i32 243

]]></Node>
<StgValue><ssdm name="tmp_20_i"/></StgValue>
</operation>

<operation id="55" st_id="12" stage="1" lat="1">
<core>NULL</core>
<MemPortIdVec></MemPortIdVec>
<condition id="-1">
<or_exp><and_exp></and_exp></or_exp>
</condition>

<Node id="36" bw="20" op_0_bw="20" op_1_bw="512" op_2_bw="32" op_3_bw="32">
<![CDATA[
VITIS_LOOP_333_1.split.i:13 %tmp_21_i = partselect i20 @_ssdm_op_PartSelect.i20.i512.i32.i32, i512 %buffered_data, i32 256, i32 275

]]></Node>
<StgValue><ssdm name="tmp_21_i"/></StgValue>
</operation>

<operation id="56" st_id="12" stage="1" lat="1">
<core>NULL</core>
<MemPortIdVec></MemPortIdVec>
<condition id="-1">
<or_exp><and_exp></and_exp></or_exp>
</condition>

<Node id="37" bw="20" op_0_bw="20" op_1_bw="512" op_2_bw="32" op_3_bw="32">
<![CDATA[
VITIS_LOOP_333_1.split.i:14 %tmp_22_i = partselect i20 @_ssdm_op_PartSelect.i20.i512.i32.i32, i512 %buffered_data, i32 288, i32 307

]]></Node>
<StgValue><ssdm name="tmp_22_i"/></StgValue>
</operation>

<operation id="57" st_id="12" stage="1" lat="1">
<core>NULL</core>
<MemPortIdVec></MemPortIdVec>
<condition id="-1">
<or_exp><and_exp></and_exp></or_exp>
</condition>

<Node id="38" bw="20" op_0_bw="20" op_1_bw="512" op_2_bw="32" op_3_bw="32">
<![CDATA[
VITIS_LOOP_333_1.split.i:15 %tmp_23_i = partselect i20 @_ssdm_op_PartSelect.i20.i512.i32.i32, i512 %buffered_data, i32 320, i32 339

]]></Node>
<StgValue><ssdm name="tmp_23_i"/></StgValue>
</operation>

<operation id="58" st_id="12" stage="1" lat="1">
<core>NULL</core>
<MemPortIdVec></MemPortIdVec>
<condition id="-1">
<or_exp><and_exp></and_exp></or_exp>
</condition>

<Node id="39" bw="20" op_0_bw="20" op_1_bw="512" op_2_bw="32" op_3_bw="32">
<![CDATA[
VITIS_LOOP_333_1.split.i:16 %tmp_24_i = partselect i20 @_ssdm_op_PartSelect.i20.i512.i32.i32, i512 %buffered_data, i32 352, i32 371

]]></Node>
<StgValue><ssdm name="tmp_24_i"/></StgValue>
</operation>

<operation id="59" st_id="12" stage="1" lat="1">
<core>NULL</core>
<MemPortIdVec></MemPortIdVec>
<condition id="-1">
<or_exp><and_exp></and_exp></or_exp>
</condition>

<Node id="40" bw="20" op_0_bw="20" op_1_bw="512" op_2_bw="32" op_3_bw="32">
<![CDATA[
VITIS_LOOP_333_1.split.i:17 %tmp_25_i = partselect i20 @_ssdm_op_PartSelect.i20.i512.i32.i32, i512 %buffered_data, i32 384, i32 403

]]></Node>
<StgValue><ssdm name="tmp_25_i"/></StgValue>
</operation>

<operation id="60" st_id="12" stage="1" lat="1">
<core>NULL</core>
<MemPortIdVec></MemPortIdVec>
<condition id="-1">
<or_exp><and_exp></and_exp></or_exp>
</condition>

<Node id="41" bw="20" op_0_bw="20" op_1_bw="512" op_2_bw="32" op_3_bw="32">
<![CDATA[
VITIS_LOOP_333_1.split.i:18 %tmp_26_i = partselect i20 @_ssdm_op_PartSelect.i20.i512.i32.i32, i512 %buffered_data, i32 416, i32 435

]]></Node>
<StgValue><ssdm name="tmp_26_i"/></StgValue>
</operation>

<operation id="61" st_id="12" stage="1" lat="1">
<core>NULL</core>
<MemPortIdVec></MemPortIdVec>
<condition id="-1">
<or_exp><and_exp></and_exp></or_exp>
</condition>

<Node id="42" bw="20" op_0_bw="20" op_1_bw="512" op_2_bw="32" op_3_bw="32">
<![CDATA[
VITIS_LOOP_333_1.split.i:19 %tmp_27_i = partselect i20 @_ssdm_op_PartSelect.i20.i512.i32.i32, i512 %buffered_data, i32 448, i32 467

]]></Node>
<StgValue><ssdm name="tmp_27_i"/></StgValue>
</operation>

<operation id="62" st_id="12" stage="1" lat="1">
<core>NULL</core>
<MemPortIdVec></MemPortIdVec>
<condition id="-1">
<or_exp><and_exp></and_exp></or_exp>
</condition>

<Node id="43" bw="20" op_0_bw="20" op_1_bw="512" op_2_bw="32" op_3_bw="32">
<![CDATA[
VITIS_LOOP_333_1.split.i:20 %tmp_28_i = partselect i20 @_ssdm_op_PartSelect.i20.i512.i32.i32, i512 %buffered_data, i32 480, i32 499

]]></Node>
<StgValue><ssdm name="tmp_28_i"/></StgValue>
</operation>
</state>

<state id="13" st_id="14">

<operation id="63" st_id="13" stage="1" lat="1">
<core>NULL</core>
<MemPortIdVec></MemPortIdVec>
<condition id="-1">
<or_exp><and_exp></and_exp></or_exp>
</condition>

<Node id="24" bw="0" op_0_bw="0" op_1_bw="32" op_2_bw="32" op_3_bw="32" op_4_bw="32" op_5_bw="0">
<![CDATA[
VITIS_LOOP_333_1.split.i:1 %specpipeline_ln322 = specpipeline void @_ssdm_op_SpecPipeline, i32 1, i32 0, i32 0, i32 0, void @empty_12

]]></Node>
<StgValue><ssdm name="specpipeline_ln322"/></StgValue>
</operation>

<operation id="64" st_id="13" stage="1" lat="1">
<core>NULL</core>
<MemPortIdVec></MemPortIdVec>
<condition id="-1">
<or_exp><and_exp></and_exp></or_exp>
</condition>

<Node id="25" bw="0" op_0_bw="0" op_1_bw="64" op_2_bw="64" op_3_bw="64">
<![CDATA[
VITIS_LOOP_333_1.split.i:2 %speclooptripcount_ln321 = speclooptripcount void @_ssdm_op_SpecLoopTripCount, i64 4096, i64 4096, i64 4096

]]></Node>
<StgValue><ssdm name="speclooptripcount_ln321"/></StgValue>
</operation>

<operation id="65" st_id="13" stage="1" lat="1">
<core>NULL</core>
<MemPortIdVec></MemPortIdVec>
<condition id="-1">
<or_exp><and_exp></and_exp></or_exp>
</condition>

<Node id="26" bw="0" op_0_bw="0" op_1_bw="0">
<![CDATA[
VITIS_LOOP_333_1.split.i:3 %specloopname_ln321 = specloopname void @_ssdm_op_SpecLoopName, void @empty_1

]]></Node>
<StgValue><ssdm name="specloopname_ln321"/></StgValue>
</operation>

<operation id="66" st_id="13" stage="1" lat="1">
<core>NULL</core>
<MemPortIdVec></MemPortIdVec>
<condition id="-1">
<or_exp><and_exp></and_exp></or_exp>
</condition>

<Node id="44" bw="500" op_0_bw="500" op_1_bw="20" op_2_bw="12" op_3_bw="20" op_4_bw="12" op_5_bw="20" op_6_bw="12" op_7_bw="20" op_8_bw="12" op_9_bw="20" op_10_bw="12" op_11_bw="20" op_12_bw="12" op_13_bw="20" op_14_bw="12" op_15_bw="20" op_16_bw="12" op_17_bw="20" op_18_bw="12" op_19_bw="20" op_20_bw="12" op_21_bw="20" op_22_bw="12" op_23_bw="20" op_24_bw="12" op_25_bw="20" op_26_bw="12" op_27_bw="20" op_28_bw="12" op_29_bw="20" op_30_bw="12" op_31_bw="20">
<![CDATA[
VITIS_LOOP_333_1.split.i:21 %tmp_29_i = bitconcatenate i500 @_ssdm_op_BitConcatenate.i500.i20.i12.i20.i12.i20.i12.i20.i12.i20.i12.i20.i12.i20.i12.i20.i12.i20.i12.i20.i12.i20.i12.i20.i12.i20.i12.i20.i12.i20.i12.i20, i20 %tmp_28_i, i12 0, i20 %tmp_27_i, i12 0, i20 %tmp_26_i, i12 0, i20 %tmp_25_i, i12 0, i20 %tmp_24_i, i12 0, i20 %tmp_23_i, i12 0, i20 %tmp_22_i, i12 0, i20 %tmp_21_i, i12 0, i20 %tmp_20_i, i12 0, i20 %tmp_19_i, i12 0, i20 %tmp_18_i, i12 0, i20 %tmp_17_i, i12 0, i20 %tmp_16_i, i12 0, i20 %tmp_15_i, i12 0, i20 %tmp_i, i12 0, i20 %trunc_ln336

]]></Node>
<StgValue><ssdm name="tmp_29_i"/></StgValue>
</operation>

<operation id="67" st_id="13" stage="1" lat="1">
<core>NULL</core>
<MemPortIdVec></MemPortIdVec>
<condition id="-1">
<or_exp><and_exp></and_exp></or_exp>
</condition>

<Node id="45" bw="512" op_0_bw="500">
<![CDATA[
VITIS_LOOP_333_1.split.i:22 %zext_ln338 = zext i500 %tmp_29_i

]]></Node>
<StgValue><ssdm name="zext_ln338"/></StgValue>
</operation>

<operation id="68" st_id="13" stage="1" lat="1">
<core>FIFO_SRL</core>
<MemPortIdVec></MemPortIdVec>
<condition id="-1">
<or_exp><and_exp></and_exp></or_exp>
</condition>

<Node id="46" bw="0" op_0_bw="0" op_1_bw="512" op_2_bw="512">
<![CDATA[
VITIS_LOOP_333_1.split.i:23 %write_ln338 = write void @_ssdm_op_Write.ap_fifo.volatile.i512P0A, i512 %s_in, i512 %zext_ln338

]]></Node>
<StgValue><ssdm name="write_ln338"/></StgValue>
</operation>

<operation id="69" st_id="13" stage="1" lat="1">
<core>NULL</core>
<MemPortIdVec></MemPortIdVec>
<condition id="-1">
<or_exp><and_exp><literal name="icmp_ln321" val="1"/>
</and_exp></or_exp>
</condition>

<Node id="52" bw="0">
<![CDATA[
load_input_wide.exit:0 %ret_ln0 = ret

]]></Node>
<StgValue><ssdm name="ret_ln0"/></StgValue>
</operation>
</state>
</state_list>


<ports>
<port id="112" name="gmem0" dir="0" iftype="4">
<core>NULL</core><StgValue><ssdm name="gmem0"/><MemPortTyVec>0 </MemPortTyVec>
</StgValue>
</port>
<port id="113" name="in_r" dir="0" iftype="0">
<core>NULL</core><StgValue><ssdm name="in_r"/></StgValue>
</port>
<port id="114" name="s_in" dir="1" iftype="3">
<core>FIFO_SRL</core><StgValue><ssdm name="s_in"/></StgValue>
</port>
</ports>


<dataflows>
<dataflow id="116" from="StgValue_115" to="i1" fromId="115" toId="16">
</dataflow>
<dataflow id="118" from="_ssdm_op_SpecInterface" to="specinterface_ln0" fromId="117" toId="17">
</dataflow>
<dataflow id="119" from="s_in" to="specinterface_ln0" fromId="114" toId="17">
</dataflow>
<dataflow id="121" from="empty_18" to="specinterface_ln0" fromId="120" toId="17">
</dataflow>
<dataflow id="123" from="StgValue_122" to="specinterface_ln0" fromId="122" toId="17">
</dataflow>
<dataflow id="124" from="StgValue_122" to="specinterface_ln0" fromId="122" toId="17">
</dataflow>
<dataflow id="126" from="empty_12" to="specinterface_ln0" fromId="125" toId="17">
</dataflow>
<dataflow id="127" from="StgValue_122" to="specinterface_ln0" fromId="122" toId="17">
</dataflow>
<dataflow id="128" from="StgValue_122" to="specinterface_ln0" fromId="122" toId="17">
</dataflow>
<dataflow id="129" from="empty_12" to="specinterface_ln0" fromId="125" toId="17">
</dataflow>
<dataflow id="130" from="empty_12" to="specinterface_ln0" fromId="125" toId="17">
</dataflow>
<dataflow id="131" from="empty_12" to="specinterface_ln0" fromId="125" toId="17">
</dataflow>
<dataflow id="132" from="StgValue_122" to="specinterface_ln0" fromId="122" toId="17">
</dataflow>
<dataflow id="133" from="StgValue_122" to="specinterface_ln0" fromId="122" toId="17">
</dataflow>
<dataflow id="134" from="StgValue_122" to="specinterface_ln0" fromId="122" toId="17">
</dataflow>
<dataflow id="135" from="StgValue_122" to="specinterface_ln0" fromId="122" toId="17">
</dataflow>
<dataflow id="136" from="empty_12" to="specinterface_ln0" fromId="125" toId="17">
</dataflow>
<dataflow id="137" from="empty_12" to="specinterface_ln0" fromId="125" toId="17">
</dataflow>
<dataflow id="139" from="StgValue_138" to="specinterface_ln0" fromId="138" toId="17">
</dataflow>
<dataflow id="140" from="StgValue_122" to="specinterface_ln0" fromId="122" toId="17">
</dataflow>
<dataflow id="141" from="StgValue_122" to="specinterface_ln0" fromId="122" toId="17">
</dataflow>
<dataflow id="142" from="_ssdm_op_SpecInterface" to="specinterface_ln0" fromId="117" toId="18">
</dataflow>
<dataflow id="143" from="s_in" to="specinterface_ln0" fromId="114" toId="18">
</dataflow>
<dataflow id="144" from="empty_18" to="specinterface_ln0" fromId="120" toId="18">
</dataflow>
<dataflow id="145" from="StgValue_122" to="specinterface_ln0" fromId="122" toId="18">
</dataflow>
<dataflow id="146" from="StgValue_122" to="specinterface_ln0" fromId="122" toId="18">
</dataflow>
<dataflow id="147" from="empty_12" to="specinterface_ln0" fromId="125" toId="18">
</dataflow>
<dataflow id="148" from="StgValue_122" to="specinterface_ln0" fromId="122" toId="18">
</dataflow>
<dataflow id="149" from="StgValue_122" to="specinterface_ln0" fromId="122" toId="18">
</dataflow>
<dataflow id="150" from="empty_12" to="specinterface_ln0" fromId="125" toId="18">
</dataflow>
<dataflow id="151" from="empty_12" to="specinterface_ln0" fromId="125" toId="18">
</dataflow>
<dataflow id="152" from="empty_12" to="specinterface_ln0" fromId="125" toId="18">
</dataflow>
<dataflow id="153" from="StgValue_122" to="specinterface_ln0" fromId="122" toId="18">
</dataflow>
<dataflow id="154" from="StgValue_122" to="specinterface_ln0" fromId="122" toId="18">
</dataflow>
<dataflow id="155" from="StgValue_122" to="specinterface_ln0" fromId="122" toId="18">
</dataflow>
<dataflow id="156" from="StgValue_122" to="specinterface_ln0" fromId="122" toId="18">
</dataflow>
<dataflow id="157" from="empty_12" to="specinterface_ln0" fromId="125" toId="18">
</dataflow>
<dataflow id="158" from="empty_12" to="specinterface_ln0" fromId="125" toId="18">
</dataflow>
<dataflow id="159" from="StgValue_138" to="specinterface_ln0" fromId="138" toId="18">
</dataflow>
<dataflow id="160" from="StgValue_122" to="specinterface_ln0" fromId="122" toId="18">
</dataflow>
<dataflow id="161" from="StgValue_122" to="specinterface_ln0" fromId="122" toId="18">
</dataflow>
<dataflow id="162" from="_ssdm_op_SpecInterface" to="specinterface_ln0" fromId="117" toId="19">
</dataflow>
<dataflow id="163" from="s_in" to="specinterface_ln0" fromId="114" toId="19">
</dataflow>
<dataflow id="164" from="empty_18" to="specinterface_ln0" fromId="120" toId="19">
</dataflow>
<dataflow id="165" from="StgValue_122" to="specinterface_ln0" fromId="122" toId="19">
</dataflow>
<dataflow id="166" from="StgValue_122" to="specinterface_ln0" fromId="122" toId="19">
</dataflow>
<dataflow id="167" from="empty_12" to="specinterface_ln0" fromId="125" toId="19">
</dataflow>
<dataflow id="168" from="StgValue_122" to="specinterface_ln0" fromId="122" toId="19">
</dataflow>
<dataflow id="169" from="StgValue_122" to="specinterface_ln0" fromId="122" toId="19">
</dataflow>
<dataflow id="170" from="empty_12" to="specinterface_ln0" fromId="125" toId="19">
</dataflow>
<dataflow id="171" from="empty_12" to="specinterface_ln0" fromId="125" toId="19">
</dataflow>
<dataflow id="172" from="empty_12" to="specinterface_ln0" fromId="125" toId="19">
</dataflow>
<dataflow id="173" from="StgValue_122" to="specinterface_ln0" fromId="122" toId="19">
</dataflow>
<dataflow id="174" from="StgValue_122" to="specinterface_ln0" fromId="122" toId="19">
</dataflow>
<dataflow id="175" from="StgValue_122" to="specinterface_ln0" fromId="122" toId="19">
</dataflow>
<dataflow id="176" from="StgValue_122" to="specinterface_ln0" fromId="122" toId="19">
</dataflow>
<dataflow id="177" from="empty_12" to="specinterface_ln0" fromId="125" toId="19">
</dataflow>
<dataflow id="178" from="empty_12" to="specinterface_ln0" fromId="125" toId="19">
</dataflow>
<dataflow id="179" from="StgValue_138" to="specinterface_ln0" fromId="138" toId="19">
</dataflow>
<dataflow id="180" from="StgValue_122" to="specinterface_ln0" fromId="122" toId="19">
</dataflow>
<dataflow id="181" from="StgValue_122" to="specinterface_ln0" fromId="122" toId="19">
</dataflow>
<dataflow id="182" from="_ssdm_op_SpecInterface" to="specinterface_ln0" fromId="117" toId="20">
</dataflow>
<dataflow id="183" from="s_in" to="specinterface_ln0" fromId="114" toId="20">
</dataflow>
<dataflow id="184" from="empty_18" to="specinterface_ln0" fromId="120" toId="20">
</dataflow>
<dataflow id="185" from="StgValue_122" to="specinterface_ln0" fromId="122" toId="20">
</dataflow>
<dataflow id="186" from="StgValue_122" to="specinterface_ln0" fromId="122" toId="20">
</dataflow>
<dataflow id="187" from="empty_12" to="specinterface_ln0" fromId="125" toId="20">
</dataflow>
<dataflow id="188" from="StgValue_122" to="specinterface_ln0" fromId="122" toId="20">
</dataflow>
<dataflow id="189" from="StgValue_122" to="specinterface_ln0" fromId="122" toId="20">
</dataflow>
<dataflow id="190" from="empty_12" to="specinterface_ln0" fromId="125" toId="20">
</dataflow>
<dataflow id="191" from="empty_12" to="specinterface_ln0" fromId="125" toId="20">
</dataflow>
<dataflow id="192" from="empty_12" to="specinterface_ln0" fromId="125" toId="20">
</dataflow>
<dataflow id="193" from="StgValue_122" to="specinterface_ln0" fromId="122" toId="20">
</dataflow>
<dataflow id="194" from="StgValue_122" to="specinterface_ln0" fromId="122" toId="20">
</dataflow>
<dataflow id="195" from="StgValue_122" to="specinterface_ln0" fromId="122" toId="20">
</dataflow>
<dataflow id="196" from="StgValue_122" to="specinterface_ln0" fromId="122" toId="20">
</dataflow>
<dataflow id="197" from="empty_12" to="specinterface_ln0" fromId="125" toId="20">
</dataflow>
<dataflow id="198" from="empty_12" to="specinterface_ln0" fromId="125" toId="20">
</dataflow>
<dataflow id="199" from="StgValue_138" to="specinterface_ln0" fromId="138" toId="20">
</dataflow>
<dataflow id="200" from="StgValue_122" to="specinterface_ln0" fromId="122" toId="20">
</dataflow>
<dataflow id="201" from="StgValue_122" to="specinterface_ln0" fromId="122" toId="20">
</dataflow>
<dataflow id="202" from="_ssdm_op_SpecInterface" to="specinterface_ln0" fromId="117" toId="21">
</dataflow>
<dataflow id="203" from="gmem0" to="specinterface_ln0" fromId="112" toId="21">
</dataflow>
<dataflow id="205" from="empty_13" to="specinterface_ln0" fromId="204" toId="21">
</dataflow>
<dataflow id="206" from="StgValue_122" to="specinterface_ln0" fromId="122" toId="21">
</dataflow>
<dataflow id="207" from="StgValue_122" to="specinterface_ln0" fromId="122" toId="21">
</dataflow>
<dataflow id="208" from="empty_12" to="specinterface_ln0" fromId="125" toId="21">
</dataflow>
<dataflow id="210" from="StgValue_209" to="specinterface_ln0" fromId="209" toId="21">
</dataflow>
<dataflow id="212" from="StgValue_211" to="specinterface_ln0" fromId="211" toId="21">
</dataflow>
<dataflow id="214" from="empty_11" to="specinterface_ln0" fromId="213" toId="21">
</dataflow>
<dataflow id="216" from="empty_10" to="specinterface_ln0" fromId="215" toId="21">
</dataflow>
<dataflow id="217" from="empty_12" to="specinterface_ln0" fromId="125" toId="21">
</dataflow>
<dataflow id="219" from="StgValue_218" to="specinterface_ln0" fromId="218" toId="21">
</dataflow>
<dataflow id="220" from="StgValue_218" to="specinterface_ln0" fromId="218" toId="21">
</dataflow>
<dataflow id="221" from="StgValue_218" to="specinterface_ln0" fromId="218" toId="21">
</dataflow>
<dataflow id="222" from="StgValue_218" to="specinterface_ln0" fromId="218" toId="21">
</dataflow>
<dataflow id="223" from="empty_12" to="specinterface_ln0" fromId="125" toId="21">
</dataflow>
<dataflow id="224" from="empty_12" to="specinterface_ln0" fromId="125" toId="21">
</dataflow>
<dataflow id="225" from="StgValue_138" to="specinterface_ln0" fromId="138" toId="21">
</dataflow>
<dataflow id="226" from="StgValue_122" to="specinterface_ln0" fromId="122" toId="21">
</dataflow>
<dataflow id="227" from="StgValue_122" to="specinterface_ln0" fromId="122" toId="21">
</dataflow>
<dataflow id="229" from="_ssdm_op_Read.ap_auto.i64" to="in_read" fromId="228" toId="22">
</dataflow>
<dataflow id="230" from="in_r" to="in_read" fromId="113" toId="22">
</dataflow>
<dataflow id="232" from="StgValue_231" to="store_ln0" fromId="231" toId="23">
</dataflow>
<dataflow id="233" from="i1" to="store_ln0" fromId="16" toId="23">
</dataflow>
<dataflow id="235" from="StgValue_234" to="first_iter_0" fromId="234" toId="25">
<condition id="-1">
<or_exp><and_exp></and_exp></or_exp>
</condition>
</dataflow>
<dataflow id="236" from="br_ln321" to="first_iter_0" fromId="24" toId="25">
</dataflow>
<dataflow id="238" from="StgValue_237" to="first_iter_0" fromId="237" toId="25">
<condition id="-1">
<or_exp><and_exp><literal name="icmp_ln321" val="0"/>
</and_exp></or_exp>
</condition>
</dataflow>
<dataflow id="239" from="br_ln321" to="first_iter_0" fromId="31" toId="25">
<BackEdge/>
</dataflow>
<dataflow id="240" from="first_iter_0" to="br_ln0" fromId="25" toId="26">
</dataflow>
<dataflow id="241" from="i1" to="i1_load" fromId="16" toId="27">
</dataflow>
<dataflow id="242" from="i1_load" to="i" fromId="27" toId="28">
</dataflow>
<dataflow id="244" from="StgValue_243" to="i" fromId="243" toId="28">
</dataflow>
<dataflow id="245" from="i1_load" to="icmp_ln321" fromId="27" toId="29">
</dataflow>
<dataflow id="247" from="StgValue_246" to="icmp_ln321" fromId="246" toId="29">
</dataflow>
<dataflow id="248" from="i" to="store_ln321" fromId="28" toId="30">
</dataflow>
<dataflow id="249" from="i1" to="store_ln321" fromId="16" toId="30">
</dataflow>
<dataflow id="250" from="icmp_ln321" to="br_ln321" fromId="29" toId="31">
</dataflow>
<dataflow id="252" from="_ssdm_op_PartSelect.i58.i64.i32.i32" to="trunc_ln" fromId="251" toId="32">
</dataflow>
<dataflow id="253" from="in_read" to="trunc_ln" fromId="22" toId="32">
</dataflow>
<dataflow id="255" from="StgValue_254" to="trunc_ln" fromId="254" toId="32">
</dataflow>
<dataflow id="257" from="StgValue_256" to="trunc_ln" fromId="256" toId="32">
</dataflow>
<dataflow id="258" from="trunc_ln" to="sext_ln321" fromId="32" toId="33">
</dataflow>
<dataflow id="259" from="gmem0" to="gmem0_addr" fromId="112" toId="34">
</dataflow>
<dataflow id="260" from="sext_ln321" to="gmem0_addr" fromId="33" toId="34">
</dataflow>
<dataflow id="262" from="_ssdm_op_ReadReq.m_axi.p1i512" to="empty" fromId="261" toId="35">
</dataflow>
<dataflow id="263" from="gmem0_addr" to="empty" fromId="34" toId="35">
</dataflow>
<dataflow id="265" from="StgValue_264" to="empty" fromId="264" toId="35">
</dataflow>
<dataflow id="266" from="_ssdm_op_ReadReq.m_axi.p1i512" to="empty" fromId="261" toId="36">
</dataflow>
<dataflow id="267" from="gmem0_addr" to="empty" fromId="34" toId="36">
</dataflow>
<dataflow id="268" from="StgValue_264" to="empty" fromId="264" toId="36">
</dataflow>
<dataflow id="269" from="_ssdm_op_ReadReq.m_axi.p1i512" to="empty" fromId="261" toId="37">
</dataflow>
<dataflow id="270" from="gmem0_addr" to="empty" fromId="34" toId="37">
</dataflow>
<dataflow id="271" from="StgValue_264" to="empty" fromId="264" toId="37">
</dataflow>
<dataflow id="272" from="_ssdm_op_ReadReq.m_axi.p1i512" to="empty" fromId="261" toId="38">
</dataflow>
<dataflow id="273" from="gmem0_addr" to="empty" fromId="34" toId="38">
</dataflow>
<dataflow id="274" from="StgValue_264" to="empty" fromId="264" toId="38">
</dataflow>
<dataflow id="275" from="_ssdm_op_ReadReq.m_axi.p1i512" to="empty" fromId="261" toId="39">
</dataflow>
<dataflow id="276" from="gmem0_addr" to="empty" fromId="34" toId="39">
</dataflow>
<dataflow id="277" from="StgValue_264" to="empty" fromId="264" toId="39">
</dataflow>
<dataflow id="278" from="_ssdm_op_ReadReq.m_axi.p1i512" to="empty" fromId="261" toId="40">
</dataflow>
<dataflow id="279" from="gmem0_addr" to="empty" fromId="34" toId="40">
</dataflow>
<dataflow id="280" from="StgValue_264" to="empty" fromId="264" toId="40">
</dataflow>
<dataflow id="281" from="_ssdm_op_ReadReq.m_axi.p1i512" to="empty" fromId="261" toId="41">
</dataflow>
<dataflow id="282" from="gmem0_addr" to="empty" fromId="34" toId="41">
</dataflow>
<dataflow id="283" from="StgValue_264" to="empty" fromId="264" toId="41">
</dataflow>
<dataflow id="284" from="_ssdm_op_ReadReq.m_axi.p1i512" to="empty" fromId="261" toId="42">
</dataflow>
<dataflow id="285" from="gmem0_addr" to="empty" fromId="34" toId="42">
</dataflow>
<dataflow id="286" from="StgValue_264" to="empty" fromId="264" toId="42">
</dataflow>
<dataflow id="287" from="_ssdm_op_ReadReq.m_axi.p1i512" to="empty" fromId="261" toId="43">
</dataflow>
<dataflow id="288" from="gmem0_addr" to="empty" fromId="34" toId="43">
</dataflow>
<dataflow id="289" from="StgValue_264" to="empty" fromId="264" toId="43">
</dataflow>
<dataflow id="290" from="_ssdm_op_ReadReq.m_axi.p1i512" to="empty" fromId="261" toId="44">
</dataflow>
<dataflow id="291" from="gmem0_addr" to="empty" fromId="34" toId="44">
</dataflow>
<dataflow id="292" from="StgValue_264" to="empty" fromId="264" toId="44">
</dataflow>
<dataflow id="294" from="_ssdm_op_Read.m_axi.p1i512" to="buffered_data" fromId="293" toId="46">
</dataflow>
<dataflow id="295" from="gmem0_addr" to="buffered_data" fromId="34" toId="46">
</dataflow>
<dataflow id="296" from="buffered_data" to="trunc_ln336" fromId="46" toId="47">
</dataflow>
<dataflow id="298" from="_ssdm_op_PartSelect.i20.i512.i32.i32" to="tmp_i" fromId="297" toId="48">
</dataflow>
<dataflow id="299" from="buffered_data" to="tmp_i" fromId="46" toId="48">
</dataflow>
<dataflow id="301" from="StgValue_300" to="tmp_i" fromId="300" toId="48">
</dataflow>
<dataflow id="303" from="StgValue_302" to="tmp_i" fromId="302" toId="48">
</dataflow>
<dataflow id="304" from="_ssdm_op_PartSelect.i20.i512.i32.i32" to="tmp_15_i" fromId="297" toId="49">
</dataflow>
<dataflow id="305" from="buffered_data" to="tmp_15_i" fromId="46" toId="49">
</dataflow>
<dataflow id="307" from="StgValue_306" to="tmp_15_i" fromId="306" toId="49">
</dataflow>
<dataflow id="309" from="StgValue_308" to="tmp_15_i" fromId="308" toId="49">
</dataflow>
<dataflow id="310" from="_ssdm_op_PartSelect.i20.i512.i32.i32" to="tmp_16_i" fromId="297" toId="50">
</dataflow>
<dataflow id="311" from="buffered_data" to="tmp_16_i" fromId="46" toId="50">
</dataflow>
<dataflow id="313" from="StgValue_312" to="tmp_16_i" fromId="312" toId="50">
</dataflow>
<dataflow id="315" from="StgValue_314" to="tmp_16_i" fromId="314" toId="50">
</dataflow>
<dataflow id="316" from="_ssdm_op_PartSelect.i20.i512.i32.i32" to="tmp_17_i" fromId="297" toId="51">
</dataflow>
<dataflow id="317" from="buffered_data" to="tmp_17_i" fromId="46" toId="51">
</dataflow>
<dataflow id="319" from="StgValue_318" to="tmp_17_i" fromId="318" toId="51">
</dataflow>
<dataflow id="321" from="StgValue_320" to="tmp_17_i" fromId="320" toId="51">
</dataflow>
<dataflow id="322" from="_ssdm_op_PartSelect.i20.i512.i32.i32" to="tmp_18_i" fromId="297" toId="52">
</dataflow>
<dataflow id="323" from="buffered_data" to="tmp_18_i" fromId="46" toId="52">
</dataflow>
<dataflow id="325" from="StgValue_324" to="tmp_18_i" fromId="324" toId="52">
</dataflow>
<dataflow id="327" from="StgValue_326" to="tmp_18_i" fromId="326" toId="52">
</dataflow>
<dataflow id="328" from="_ssdm_op_PartSelect.i20.i512.i32.i32" to="tmp_19_i" fromId="297" toId="53">
</dataflow>
<dataflow id="329" from="buffered_data" to="tmp_19_i" fromId="46" toId="53">
</dataflow>
<dataflow id="331" from="StgValue_330" to="tmp_19_i" fromId="330" toId="53">
</dataflow>
<dataflow id="333" from="StgValue_332" to="tmp_19_i" fromId="332" toId="53">
</dataflow>
<dataflow id="334" from="_ssdm_op_PartSelect.i20.i512.i32.i32" to="tmp_20_i" fromId="297" toId="54">
</dataflow>
<dataflow id="335" from="buffered_data" to="tmp_20_i" fromId="46" toId="54">
</dataflow>
<dataflow id="337" from="StgValue_336" to="tmp_20_i" fromId="336" toId="54">
</dataflow>
<dataflow id="339" from="StgValue_338" to="tmp_20_i" fromId="338" toId="54">
</dataflow>
<dataflow id="340" from="_ssdm_op_PartSelect.i20.i512.i32.i32" to="tmp_21_i" fromId="297" toId="55">
</dataflow>
<dataflow id="341" from="buffered_data" to="tmp_21_i" fromId="46" toId="55">
</dataflow>
<dataflow id="343" from="StgValue_342" to="tmp_21_i" fromId="342" toId="55">
</dataflow>
<dataflow id="345" from="StgValue_344" to="tmp_21_i" fromId="344" toId="55">
</dataflow>
<dataflow id="346" from="_ssdm_op_PartSelect.i20.i512.i32.i32" to="tmp_22_i" fromId="297" toId="56">
</dataflow>
<dataflow id="347" from="buffered_data" to="tmp_22_i" fromId="46" toId="56">
</dataflow>
<dataflow id="349" from="StgValue_348" to="tmp_22_i" fromId="348" toId="56">
</dataflow>
<dataflow id="351" from="StgValue_350" to="tmp_22_i" fromId="350" toId="56">
</dataflow>
<dataflow id="352" from="_ssdm_op_PartSelect.i20.i512.i32.i32" to="tmp_23_i" fromId="297" toId="57">
</dataflow>
<dataflow id="353" from="buffered_data" to="tmp_23_i" fromId="46" toId="57">
</dataflow>
<dataflow id="355" from="StgValue_354" to="tmp_23_i" fromId="354" toId="57">
</dataflow>
<dataflow id="357" from="StgValue_356" to="tmp_23_i" fromId="356" toId="57">
</dataflow>
<dataflow id="358" from="_ssdm_op_PartSelect.i20.i512.i32.i32" to="tmp_24_i" fromId="297" toId="58">
</dataflow>
<dataflow id="359" from="buffered_data" to="tmp_24_i" fromId="46" toId="58">
</dataflow>
<dataflow id="361" from="StgValue_360" to="tmp_24_i" fromId="360" toId="58">
</dataflow>
<dataflow id="363" from="StgValue_362" to="tmp_24_i" fromId="362" toId="58">
</dataflow>
<dataflow id="364" from="_ssdm_op_PartSelect.i20.i512.i32.i32" to="tmp_25_i" fromId="297" toId="59">
</dataflow>
<dataflow id="365" from="buffered_data" to="tmp_25_i" fromId="46" toId="59">
</dataflow>
<dataflow id="367" from="StgValue_366" to="tmp_25_i" fromId="366" toId="59">
</dataflow>
<dataflow id="369" from="StgValue_368" to="tmp_25_i" fromId="368" toId="59">
</dataflow>
<dataflow id="370" from="_ssdm_op_PartSelect.i20.i512.i32.i32" to="tmp_26_i" fromId="297" toId="60">
</dataflow>
<dataflow id="371" from="buffered_data" to="tmp_26_i" fromId="46" toId="60">
</dataflow>
<dataflow id="373" from="StgValue_372" to="tmp_26_i" fromId="372" toId="60">
</dataflow>
<dataflow id="375" from="StgValue_374" to="tmp_26_i" fromId="374" toId="60">
</dataflow>
<dataflow id="376" from="_ssdm_op_PartSelect.i20.i512.i32.i32" to="tmp_27_i" fromId="297" toId="61">
</dataflow>
<dataflow id="377" from="buffered_data" to="tmp_27_i" fromId="46" toId="61">
</dataflow>
<dataflow id="379" from="StgValue_378" to="tmp_27_i" fromId="378" toId="61">
</dataflow>
<dataflow id="381" from="StgValue_380" to="tmp_27_i" fromId="380" toId="61">
</dataflow>
<dataflow id="382" from="_ssdm_op_PartSelect.i20.i512.i32.i32" to="tmp_28_i" fromId="297" toId="62">
</dataflow>
<dataflow id="383" from="buffered_data" to="tmp_28_i" fromId="46" toId="62">
</dataflow>
<dataflow id="385" from="StgValue_384" to="tmp_28_i" fromId="384" toId="62">
</dataflow>
<dataflow id="387" from="StgValue_386" to="tmp_28_i" fromId="386" toId="62">
</dataflow>
<dataflow id="389" from="_ssdm_op_SpecPipeline" to="specpipeline_ln322" fromId="388" toId="63">
</dataflow>
<dataflow id="390" from="StgValue_115" to="specpipeline_ln322" fromId="115" toId="63">
</dataflow>
<dataflow id="391" from="StgValue_122" to="specpipeline_ln322" fromId="122" toId="63">
</dataflow>
<dataflow id="392" from="StgValue_122" to="specpipeline_ln322" fromId="122" toId="63">
</dataflow>
<dataflow id="393" from="StgValue_122" to="specpipeline_ln322" fromId="122" toId="63">
</dataflow>
<dataflow id="394" from="empty_12" to="specpipeline_ln322" fromId="125" toId="63">
</dataflow>
<dataflow id="396" from="_ssdm_op_SpecLoopTripCount" to="speclooptripcount_ln321" fromId="395" toId="64">
</dataflow>
<dataflow id="397" from="StgValue_264" to="speclooptripcount_ln321" fromId="264" toId="64">
</dataflow>
<dataflow id="398" from="StgValue_264" to="speclooptripcount_ln321" fromId="264" toId="64">
</dataflow>
<dataflow id="399" from="StgValue_264" to="speclooptripcount_ln321" fromId="264" toId="64">
</dataflow>
<dataflow id="401" from="_ssdm_op_SpecLoopName" to="specloopname_ln321" fromId="400" toId="65">
</dataflow>
<dataflow id="403" from="empty_1" to="specloopname_ln321" fromId="402" toId="65">
</dataflow>
<dataflow id="405" from="_ssdm_op_BitConcatenate.i500.i20.i12.i20.i12.i20.i12.i20.i12.i20.i12.i20.i12.i20.i12.i20.i12.i20.i12.i20.i12.i20.i12.i20.i12.i20.i12.i20.i12.i20.i12.i20" to="tmp_29_i" fromId="404" toId="66">
</dataflow>
<dataflow id="406" from="tmp_28_i" to="tmp_29_i" fromId="62" toId="66">
</dataflow>
<dataflow id="407" from="StgValue_231" to="tmp_29_i" fromId="231" toId="66">
</dataflow>
<dataflow id="408" from="tmp_27_i" to="tmp_29_i" fromId="61" toId="66">
</dataflow>
<dataflow id="409" from="StgValue_231" to="tmp_29_i" fromId="231" toId="66">
</dataflow>
<dataflow id="410" from="tmp_26_i" to="tmp_29_i" fromId="60" toId="66">
</dataflow>
<dataflow id="411" from="StgValue_231" to="tmp_29_i" fromId="231" toId="66">
</dataflow>
<dataflow id="412" from="tmp_25_i" to="tmp_29_i" fromId="59" toId="66">
</dataflow>
<dataflow id="413" from="StgValue_231" to="tmp_29_i" fromId="231" toId="66">
</dataflow>
<dataflow id="414" from="tmp_24_i" to="tmp_29_i" fromId="58" toId="66">
</dataflow>
<dataflow id="415" from="StgValue_231" to="tmp_29_i" fromId="231" toId="66">
</dataflow>
<dataflow id="416" from="tmp_23_i" to="tmp_29_i" fromId="57" toId="66">
</dataflow>
<dataflow id="417" from="StgValue_231" to="tmp_29_i" fromId="231" toId="66">
</dataflow>
<dataflow id="418" from="tmp_22_i" to="tmp_29_i" fromId="56" toId="66">
</dataflow>
<dataflow id="419" from="StgValue_231" to="tmp_29_i" fromId="231" toId="66">
</dataflow>
<dataflow id="420" from="tmp_21_i" to="tmp_29_i" fromId="55" toId="66">
</dataflow>
<dataflow id="421" from="StgValue_231" to="tmp_29_i" fromId="231" toId="66">
</dataflow>
<dataflow id="422" from="tmp_20_i" to="tmp_29_i" fromId="54" toId="66">
</dataflow>
<dataflow id="423" from="StgValue_231" to="tmp_29_i" fromId="231" toId="66">
</dataflow>
<dataflow id="424" from="tmp_19_i" to="tmp_29_i" fromId="53" toId="66">
</dataflow>
<dataflow id="425" from="StgValue_231" to="tmp_29_i" fromId="231" toId="66">
</dataflow>
<dataflow id="426" from="tmp_18_i" to="tmp_29_i" fromId="52" toId="66">
</dataflow>
<dataflow id="427" from="StgValue_231" to="tmp_29_i" fromId="231" toId="66">
</dataflow>
<dataflow id="428" from="tmp_17_i" to="tmp_29_i" fromId="51" toId="66">
</dataflow>
<dataflow id="429" from="StgValue_231" to="tmp_29_i" fromId="231" toId="66">
</dataflow>
<dataflow id="430" from="tmp_16_i" to="tmp_29_i" fromId="50" toId="66">
</dataflow>
<dataflow id="431" from="StgValue_231" to="tmp_29_i" fromId="231" toId="66">
</dataflow>
<dataflow id="432" from="tmp_15_i" to="tmp_29_i" fromId="49" toId="66">
</dataflow>
<dataflow id="433" from="StgValue_231" to="tmp_29_i" fromId="231" toId="66">
</dataflow>
<dataflow id="434" from="tmp_i" to="tmp_29_i" fromId="48" toId="66">
</dataflow>
<dataflow id="435" from="StgValue_231" to="tmp_29_i" fromId="231" toId="66">
</dataflow>
<dataflow id="436" from="trunc_ln336" to="tmp_29_i" fromId="47" toId="66">
</dataflow>
<dataflow id="437" from="tmp_29_i" to="zext_ln338" fromId="66" toId="67">
</dataflow>
<dataflow id="439" from="_ssdm_op_Write.ap_fifo.volatile.i512P0A" to="write_ln338" fromId="438" toId="68">
</dataflow>
<dataflow id="440" from="s_in" to="write_ln338" fromId="114" toId="68">
</dataflow>
<dataflow id="441" from="zext_ln338" to="write_ln338" fromId="67" toId="68">
</dataflow>
<dataflow id="442" from="first_iter_0" to="StgValue_3" fromId="25" toId="3">
</dataflow>
<dataflow id="443" from="first_iter_0" to="StgValue_4" fromId="25" toId="4">
</dataflow>
<dataflow id="444" from="first_iter_0" to="StgValue_5" fromId="25" toId="5">
</dataflow>
<dataflow id="445" from="first_iter_0" to="StgValue_6" fromId="25" toId="6">
</dataflow>
<dataflow id="446" from="first_iter_0" to="StgValue_7" fromId="25" toId="7">
</dataflow>
<dataflow id="447" from="first_iter_0" to="StgValue_8" fromId="25" toId="8">
</dataflow>
<dataflow id="448" from="first_iter_0" to="StgValue_9" fromId="25" toId="9">
</dataflow>
<dataflow id="449" from="first_iter_0" to="StgValue_10" fromId="25" toId="10">
</dataflow>
<dataflow id="450" from="first_iter_0" to="StgValue_11" fromId="25" toId="11">
</dataflow>
<dataflow id="451" from="first_iter_0" to="StgValue_12" fromId="25" toId="12">
</dataflow>
<dataflow id="452" from="icmp_ln321" to="StgValue_14" fromId="29" toId="14">
</dataflow>
<dataflow id="453" from="icmp_ln321" to="StgValue_2" fromId="29" toId="2">
</dataflow>
<dataflow id="454" from="icmp_ln321" to="StgValue_3" fromId="29" toId="3">
</dataflow>
<dataflow id="455" from="icmp_ln321" to="StgValue_4" fromId="29" toId="4">
</dataflow>
<dataflow id="456" from="icmp_ln321" to="StgValue_5" fromId="29" toId="5">
</dataflow>
<dataflow id="457" from="icmp_ln321" to="StgValue_6" fromId="29" toId="6">
</dataflow>
<dataflow id="458" from="icmp_ln321" to="StgValue_7" fromId="29" toId="7">
</dataflow>
<dataflow id="459" from="icmp_ln321" to="StgValue_8" fromId="29" toId="8">
</dataflow>
<dataflow id="460" from="icmp_ln321" to="StgValue_9" fromId="29" toId="9">
</dataflow>
<dataflow id="461" from="icmp_ln321" to="StgValue_10" fromId="29" toId="10">
</dataflow>
<dataflow id="462" from="icmp_ln321" to="StgValue_11" fromId="29" toId="11">
</dataflow>
<dataflow id="463" from="icmp_ln321" to="StgValue_12" fromId="29" toId="12">
</dataflow>
<dataflow id="464" from="icmp_ln321" to="StgValue_13" fromId="29" toId="13">
</dataflow>
</dataflows>


</stg>
