<profile>

<ReportVersion>
<Version>2025.1.1</Version>
</ReportVersion>

<UserAssignments>
<unit>ns</unit>
<ProductFamily>zynquplus</ProductFamily>
<Part>xczu3eg-sbva484-1-e</Part>
<TopModelName>top_kernel_Pipeline_VITIS_LOOP_280_6_VITIS_LOOP_281_7</TopModelName>
<TargetClockPeriod>10.00</TargetClockPeriod>
<ClockUncertainty>2.70</ClockUncertainty>
<FlowTarget>vivado</FlowTarget>
</UserAssignments>

<PerformanceEstimates>
<PipelineType>loop auto-rewind stp (delay=0 cycles)</PipelineType>
<SummaryOfTimingAnalysis>
<unit>ns</unit>
<EstimatedClockPeriod>7.300</EstimatedClockPeriod>
</SummaryOfTimingAnalysis>
<SummaryOfOverallLatency>
<unit>clock cycles</unit>
<Best-caseLatency>65550</Best-caseLatency>
<Average-caseLatency>65550</Average-caseLatency>
<Worst-caseLatency>65550</Worst-caseLatency>
<Best-caseRealTimeLatency>0.655 ms</Best-caseRealTimeLatency>
<Average-caseRealTimeLatency>0.655 ms</Average-caseRealTimeLatency>
<Worst-caseRealTimeLatency>0.655 ms</Worst-caseRealTimeLatency>
<Interval-min>65537</Interval-min>
<Interval-max>65537</Interval-max>
<PerformancePragma>-</PerformancePragma>
</SummaryOfOverallLatency>
<SummaryOfLoopLatency>
<VITIS_LOOP_280_6_VITIS_LOOP_281_7>
<Slack>7.30</Slack>
<TripCount>65536</TripCount>
<isPerfectNested>0</isPerfectNested>
<Latency>65548</Latency>
<AbsoluteTimeLatency>655480</AbsoluteTimeLatency>
<PipelineII>1</PipelineII>
<PipelineDepth>14</PipelineDepth>
<PerformancePragma>-</PerformancePragma>
<InstanceList>
</InstanceList>
</VITIS_LOOP_280_6_VITIS_LOOP_281_7>
</SummaryOfLoopLatency>
<SummaryOfViolations>
<IssueType>-</IssueType>
<ViolationType>-</ViolationType>
<SourceLocation>top.cpp:281</SourceLocation>
<SummaryOfLoopViolations>
<VITIS_LOOP_280_6_VITIS_LOOP_281_7>
<Name>VITIS_LOOP_280_6_VITIS_LOOP_281_7</Name>
<IssueType>-</IssueType>
<ViolationType>-</ViolationType>
<SourceLocation>top.cpp:280</SourceLocation>
</VITIS_LOOP_280_6_VITIS_LOOP_281_7>
</SummaryOfLoopViolations>
</SummaryOfViolations>
</PerformanceEstimates>

<AreaEstimates>
<Resources>
<DSP>1</DSP>
<FF>529</FF>
<LUT>641</LUT>
<BRAM_18K>0</BRAM_18K>
<URAM>0</URAM>
</Resources>
<AvailableResources>
<BRAM_18K>432</BRAM_18K>
<DSP>360</DSP>
<FF>141120</FF>
<LUT>70560</LUT>
<URAM>0</URAM>
</AvailableResources>
</AreaEstimates>

<InterfaceSummary>
<RtlPorts>
<name>ap_clk</name>
<Object>top_kernel_Pipeline_VITIS_LOOP_280_6_VITIS_LOOP_281_7</Object>
<Type>return value</Type>
<Scope></Scope>
<IOProtocol>ap_ctrl_hs</IOProtocol>
<IOConfig></IOConfig>
<Dir>in</Dir>
<Bits>1</Bits>
<Attribute>control</Attribute>
</RtlPorts>
<RtlPorts>
<name>ap_rst</name>
<Object>top_kernel_Pipeline_VITIS_LOOP_280_6_VITIS_LOOP_281_7</Object>
<Type>return value</Type>
<Scope></Scope>
<IOProtocol>ap_ctrl_hs</IOProtocol>
<IOConfig></IOConfig>
<Dir>in</Dir>
<Bits>1</Bits>
<Attribute>control</Attribute>
</RtlPorts>
<RtlPorts>
<name>ap_start</name>
<Object>top_kernel_Pipeline_VITIS_LOOP_280_6_VITIS_LOOP_281_7</Object>
<Type>return value</Type>
<Scope></Scope>
<IOProtocol>ap_ctrl_hs</IOProtocol>
<IOConfig></IOConfig>
<Dir>in</Dir>
<Bits>1</Bits>
<Attribute>control</Attribute>
</RtlPorts>
<RtlPorts>
<name>ap_done</name>
<Object>top_kernel_Pipeline_VITIS_LOOP_280_6_VITIS_LOOP_281_7</Object>
<Type>return value</Type>
<Scope></Scope>
<IOProtocol>ap_ctrl_hs</IOProtocol>
<IOConfig></IOConfig>
<Dir>out</Dir>
<Bits>1</Bits>
<Attribute>control</Attribute>
</RtlPorts>
<RtlPorts>
<name>ap_idle</name>
<Object>top_kernel_Pipeline_VITIS_LOOP_280_6_VITIS_LOOP_281_7</Object>
<Type>return value</Type>
<Scope></Scope>
<IOProtocol>ap_ctrl_hs</IOProtocol>
<IOConfig></IOConfig>
<Dir>out</Dir>
<Bits>1</Bits>
<Attribute>control</Attribute>
</RtlPorts>
<RtlPorts>
<name>ap_ready</name>
<Object>top_kernel_Pipeline_VITIS_LOOP_280_6_VITIS_LOOP_281_7</Object>
<Type>return value</Type>
<Scope></Scope>
<IOProtocol>ap_ctrl_hs</IOProtocol>
<IOConfig></IOConfig>
<Dir>out</Dir>
<Bits>1</Bits>
<Attribute>control</Attribute>
</RtlPorts>
<RtlPorts>
<name>m_axi_gmem1_0_AWVALID</name>
<Object>gmem1</Object>
<Type>pointer</Type>
<Scope></Scope>
<IOProtocol>m_axi</IOProtocol>
<IOConfig></IOConfig>
<Dir>out</Dir>
<Bits>1</Bits>
<Attribute>unknown</Attribute>
</RtlPorts>
<RtlPorts>
<name>m_axi_gmem1_0_AWREADY</name>
<Object>gmem1</Object>
<Type>pointer</Type>
<Scope></Scope>
<IOProtocol>m_axi</IOProtocol>
<IOConfig></IOConfig>
<Dir>in</Dir>
<Bits>1</Bits>
<Attribute>unknown</Attribute>
</RtlPorts>
<RtlPorts>
<name>m_axi_gmem1_0_AWADDR</name>
<Object>gmem1</Object>
<Type>pointer</Type>
<Scope></Scope>
<IOProtocol>m_axi</IOProtocol>
<IOConfig></IOConfig>
<Dir>out</Dir>
<Bits>64</Bits>
<Attribute>unknown</Attribute>
</RtlPorts>
<RtlPorts>
<name>m_axi_gmem1_0_AWID</name>
<Object>gmem1</Object>
<Type>pointer</Type>
<Scope></Scope>
<IOProtocol>m_axi</IOProtocol>
<IOConfig></IOConfig>
<Dir>out</Dir>
<Bits>1</Bits>
<Attribute>unknown</Attribute>
</RtlPorts>
<RtlPorts>
<name>m_axi_gmem1_0_AWLEN</name>
<Object>gmem1</Object>
<Type>pointer</Type>
<Scope></Scope>
<IOProtocol>m_axi</IOProtocol>
<IOConfig></IOConfig>
<Dir>out</Dir>
<Bits>32</Bits>
<Attribute>unknown</Attribute>
</RtlPorts>
<RtlPorts>
<name>m_axi_gmem1_0_AWSIZE</name>
<Object>gmem1</Object>
<Type>pointer</Type>
<Scope></Scope>
<IOProtocol>m_axi</IOProtocol>
<IOConfig></IOConfig>
<Dir>out</Dir>
<Bits>3</Bits>
<Attribute>unknown</Attribute>
</RtlPorts>
<RtlPorts>
<name>m_axi_gmem1_0_AWBURST</name>
<Object>gmem1</Object>
<Type>pointer</Type>
<Scope></Scope>
<IOProtocol>m_axi</IOProtocol>
<IOConfig></IOConfig>
<Dir>out</Dir>
<Bits>2</Bits>
<Attribute>unknown</Attribute>
</RtlPorts>
<RtlPorts>
<name>m_axi_gmem1_0_AWLOCK</name>
<Object>gmem1</Object>
<Type>pointer</Type>
<Scope></Scope>
<IOProtocol>m_axi</IOProtocol>
<IOConfig></IOConfig>
<Dir>out</Dir>
<Bits>2</Bits>
<Attribute>unknown</Attribute>
</RtlPorts>
<RtlPorts>
<name>m_axi_gmem1_0_AWCACHE</name>
<Object>gmem1</Object>
<Type>pointer</Type>
<Scope></Scope>
<IOProtocol>m_axi</IOProtocol>
<IOConfig></IOConfig>
<Dir>out</Dir>
<Bits>4</Bits>
<Attribute>unknown</Attribute>
</RtlPorts>
<RtlPorts>
<name>m_axi_gmem1_0_AWPROT</name>
<Object>gmem1</Object>
<Type>pointer</Type>
<Scope></Scope>
<IOProtocol>m_axi</IOProtocol>
<IOConfig></IOConfig>
<Dir>out</Dir>
<Bits>3</Bits>
<Attribute>unknown</Attribute>
</RtlPorts>
<RtlPorts>
<name>m_axi_gmem1_0_AWQOS</name>
<Object>gmem1</Object>
<Type>pointer</Type>
<Scope></Scope>
<IOProtocol>m_axi</IOProtocol>
<IOConfig></IOConfig>
<Dir>out</Dir>
<Bits>4</Bits>
<Attribute>unknown</Attribute>
</RtlPorts>
<RtlPorts>
<name>m_axi_gmem1_0_AWREGION</name>
<Object>gmem1</Object>
<Type>pointer</Type>
<Scope></Scope>
<IOProtocol>m_axi</IOProtocol>
<IOConfig></IOConfig>
<Dir>out</Dir>
<Bits>4</Bits>
<Attribute>unknown</Attribute>
</RtlPorts>
<RtlPorts>
<name>m_axi_gmem1_0_AWUSER</name>
<Object>gmem1</Object>
<Type>pointer</Type>
<Scope></Scope>
<IOProtocol>m_axi</IOProtocol>
<IOConfig></IOConfig>
<Dir>out</Dir>
<Bits>1</Bits>
<Attribute>unknown</Attribute>
</RtlPorts>
<RtlPorts>
<name>m_axi_gmem1_0_WVALID</name>
<Object>gmem1</Object>
<Type>pointer</Type>
<Scope></Scope>
<IOProtocol>m_axi</IOProtocol>
<IOConfig></IOConfig>
<Dir>out</Dir>
<Bits>1</Bits>
<Attribute>unknown</Attribute>
</RtlPorts>
<RtlPorts>
<name>m_axi_gmem1_0_WREADY</name>
<Object>gmem1</Object>
<Type>pointer</Type>
<Scope></Scope>
<IOProtocol>m_axi</IOProtocol>
<IOConfig></IOConfig>
<Dir>in</Dir>
<Bits>1</Bits>
<Attribute>unknown</Attribute>
</RtlPorts>
<RtlPorts>
<name>m_axi_gmem1_0_WDATA</name>
<Object>gmem1</Object>
<Type>pointer</Type>
<Scope></Scope>
<IOProtocol>m_axi</IOProtocol>
<IOConfig></IOConfig>
<Dir>out</Dir>
<Bits>32</Bits>
<Attribute>unknown</Attribute>
</RtlPorts>
<RtlPorts>
<name>m_axi_gmem1_0_WSTRB</name>
<Object>gmem1</Object>
<Type>pointer</Type>
<Scope></Scope>
<IOProtocol>m_axi</IOProtocol>
<IOConfig></IOConfig>
<Dir>out</Dir>
<Bits>4</Bits>
<Attribute>unknown</Attribute>
</RtlPorts>
<RtlPorts>
<name>m_axi_gmem1_0_WLAST</name>
<Object>gmem1</Object>
<Type>pointer</Type>
<Scope></Scope>
<IOProtocol>m_axi</IOProtocol>
<IOConfig></IOConfig>
<Dir>out</Dir>
<Bits>1</Bits>
<Attribute>unknown</Attribute>
</RtlPorts>
<RtlPorts>
<name>m_axi_gmem1_0_WID</name>
<Object>gmem1</Object>
<Type>pointer</Type>
<Scope></Scope>
<IOProtocol>m_axi</IOProtocol>
<IOConfig></IOConfig>
<Dir>out</Dir>
<Bits>1</Bits>
<Attribute>unknown</Attribute>
</RtlPorts>
<RtlPorts>
<name>m_axi_gmem1_0_WUSER</name>
<Object>gmem1</Object>
<Type>pointer</Type>
<Scope></Scope>
<IOProtocol>m_axi</IOProtocol>
<IOConfig></IOConfig>
<Dir>out</Dir>
<Bits>1</Bits>
<Attribute>unknown</Attribute>
</RtlPorts>
<RtlPorts>
<name>m_axi_gmem1_0_ARVALID</name>
<Object>gmem1</Object>
<Type>pointer</Type>
<Scope></Scope>
<IOProtocol>m_axi</IOProtocol>
<IOConfig></IOConfig>
<Dir>out</Dir>
<Bits>1</Bits>
<Attribute>unknown</Attribute>
</RtlPorts>
<RtlPorts>
<name>m_axi_gmem1_0_ARREADY</name>
<Object>gmem1</Object>
<Type>pointer</Type>
<Scope></Scope>
<IOProtocol>m_axi</IOProtocol>
<IOConfig></IOConfig>
<Dir>in</Dir>
<Bits>1</Bits>
<Attribute>unknown</Attribute>
</RtlPorts>
<RtlPorts>
<name>m_axi_gmem1_0_ARADDR</name>
<Object>gmem1</Object>
<Type>pointer</Type>
<Scope></Scope>
<IOProtocol>m_axi</IOProtocol>
<IOConfig></IOConfig>
<Dir>out</Dir>
<Bits>64</Bits>
<Attribute>unknown</Attribute>
</RtlPorts>
<RtlPorts>
<name>m_axi_gmem1_0_ARID</name>
<Object>gmem1</Object>
<Type>pointer</Type>
<Scope></Scope>
<IOProtocol>m_axi</IOProtocol>
<IOConfig></IOConfig>
<Dir>out</Dir>
<Bits>1</Bits>
<Attribute>unknown</Attribute>
</RtlPorts>
<RtlPorts>
<name>m_axi_gmem1_0_ARLEN</name>
<Object>gmem1</Object>
<Type>pointer</Type>
<Scope></Scope>
<IOProtocol>m_axi</IOProtocol>
<IOConfig></IOConfig>
<Dir>out</Dir>
<Bits>32</Bits>
<Attribute>unknown</Attribute>
</RtlPorts>
<RtlPorts>
<name>m_axi_gmem1_0_ARSIZE</name>
<Object>gmem1</Object>
<Type>pointer</Type>
<Scope></Scope>
<IOProtocol>m_axi</IOProtocol>
<IOConfig></IOConfig>
<Dir>out</Dir>
<Bits>3</Bits>
<Attribute>unknown</Attribute>
</RtlPorts>
<RtlPorts>
<name>m_axi_gmem1_0_ARBURST</name>
<Object>gmem1</Object>
<Type>pointer</Type>
<Scope></Scope>
<IOProtocol>m_axi</IOProtocol>
<IOConfig></IOConfig>
<Dir>out</Dir>
<Bits>2</Bits>
<Attribute>unknown</Attribute>
</RtlPorts>
<RtlPorts>
<name>m_axi_gmem1_0_ARLOCK</name>
<Object>gmem1</Object>
<Type>pointer</Type>
<Scope></Scope>
<IOProtocol>m_axi</IOProtocol>
<IOConfig></IOConfig>
<Dir>out</Dir>
<Bits>2</Bits>
<Attribute>unknown</Attribute>
</RtlPorts>
<RtlPorts>
<name>m_axi_gmem1_0_ARCACHE</name>
<Object>gmem1</Object>
<Type>pointer</Type>
<Scope></Scope>
<IOProtocol>m_axi</IOProtocol>
<IOConfig></IOConfig>
<Dir>out</Dir>
<Bits>4</Bits>
<Attribute>unknown</Attribute>
</RtlPorts>
<RtlPorts>
<name>m_axi_gmem1_0_ARPROT</name>
<Object>gmem1</Object>
<Type>pointer</Type>
<Scope></Scope>
<IOProtocol>m_axi</IOProtocol>
<IOConfig></IOConfig>
<Dir>out</Dir>
<Bits>3</Bits>
<Attribute>unknown</Attribute>
</RtlPorts>
<RtlPorts>
<name>m_axi_gmem1_0_ARQOS</name>
<Object>gmem1</Object>
<Type>pointer</Type>
<Scope></Scope>
<IOProtocol>m_axi</IOProtocol>
<IOConfig></IOConfig>
<Dir>out</Dir>
<Bits>4</Bits>
<Attribute>unknown</Attribute>
</RtlPorts>
<RtlPorts>
<name>m_axi_gmem1_0_ARREGION</name>
<Object>gmem1</Object>
<Type>pointer</Type>
<Scope></Scope>
<IOProtocol>m_axi</IOProtocol>
<IOConfig></IOConfig>
<Dir>out</Dir>
<Bits>4</Bits>
<Attribute>unknown</Attribute>
</RtlPorts>
<RtlPorts>
<name>m_axi_gmem1_0_ARUSER</name>
<Object>gmem1</Object>
<Type>pointer</Type>
<Scope></Scope>
<IOProtocol>m_axi</IOProtocol>
<IOConfig></IOConfig>
<Dir>out</Dir>
<Bits>1</Bits>
<Attribute>unknown</Attribute>
</RtlPorts>
<RtlPorts>
<name>m_axi_gmem1_0_RVALID</name>
<Object>gmem1</Object>
<Type>pointer</Type>
<Scope></Scope>
<IOProtocol>m_axi</IOProtocol>
<IOConfig></IOConfig>
<Dir>in</Dir>
<Bits>1</Bits>
<Attribute>unknown</Attribute>
</RtlPorts>
<RtlPorts>
<name>m_axi_gmem1_0_RREADY</name>
<Object>gmem1</Object>
<Type>pointer</Type>
<Scope></Scope>
<IOProtocol>m_axi</IOProtocol>
<IOConfig></IOConfig>
<Dir>out</Dir>
<Bits>1</Bits>
<Attribute>unknown</Attribute>
</RtlPorts>
<RtlPorts>
<name>m_axi_gmem1_0_RDATA</name>
<Object>gmem1</Object>
<Type>pointer</Type>
<Scope></Scope>
<IOProtocol>m_axi</IOProtocol>
<IOConfig></IOConfig>
<Dir>in</Dir>
<Bits>32</Bits>
<Attribute>unknown</Attribute>
</RtlPorts>
<RtlPorts>
<name>m_axi_gmem1_0_RLAST</name>
<Object>gmem1</Object>
<Type>pointer</Type>
<Scope></Scope>
<IOProtocol>m_axi</IOProtocol>
<IOConfig></IOConfig>
<Dir>in</Dir>
<Bits>1</Bits>
<Attribute>unknown</Attribute>
</RtlPorts>
<RtlPorts>
<name>m_axi_gmem1_0_RID</name>
<Object>gmem1</Object>
<Type>pointer</Type>
<Scope></Scope>
<IOProtocol>m_axi</IOProtocol>
<IOConfig></IOConfig>
<Dir>in</Dir>
<Bits>1</Bits>
<Attribute>unknown</Attribute>
</RtlPorts>
<RtlPorts>
<name>m_axi_gmem1_0_RFIFONUM</name>
<Object>gmem1</Object>
<Type>pointer</Type>
<Scope></Scope>
<IOProtocol>m_axi</IOProtocol>
<IOConfig></IOConfig>
<Dir>in</Dir>
<Bits>9</Bits>
<Attribute>unknown</Attribute>
</RtlPorts>
<RtlPorts>
<name>m_axi_gmem1_0_RUSER</name>
<Object>gmem1</Object>
<Type>pointer</Type>
<Scope></Scope>
<IOProtocol>m_axi</IOProtocol>
<IOConfig></IOConfig>
<Dir>in</Dir>
<Bits>1</Bits>
<Attribute>unknown</Attribute>
</RtlPorts>
<RtlPorts>
<name>m_axi_gmem1_0_RRESP</name>
<Object>gmem1</Object>
<Type>pointer</Type>
<Scope></Scope>
<IOProtocol>m_axi</IOProtocol>
<IOConfig></IOConfig>
<Dir>in</Dir>
<Bits>2</Bits>
<Attribute>unknown</Attribute>
</RtlPorts>
<RtlPorts>
<name>m_axi_gmem1_0_BVALID</name>
<Object>gmem1</Object>
<Type>pointer</Type>
<Scope></Scope>
<IOProtocol>m_axi</IOProtocol>
<IOConfig></IOConfig>
<Dir>in</Dir>
<Bits>1</Bits>
<Attribute>unknown</Attribute>
</RtlPorts>
<RtlPorts>
<name>m_axi_gmem1_0_BREADY</name>
<Object>gmem1</Object>
<Type>pointer</Type>
<Scope></Scope>
<IOProtocol>m_axi</IOProtocol>
<IOConfig></IOConfig>
<Dir>out</Dir>
<Bits>1</Bits>
<Attribute>unknown</Attribute>
</RtlPorts>
<RtlPorts>
<name>m_axi_gmem1_0_BRESP</name>
<Object>gmem1</Object>
<Type>pointer</Type>
<Scope></Scope>
<IOProtocol>m_axi</IOProtocol>
<IOConfig></IOConfig>
<Dir>in</Dir>
<Bits>2</Bits>
<Attribute>unknown</Attribute>
</RtlPorts>
<RtlPorts>
<name>m_axi_gmem1_0_BID</name>
<Object>gmem1</Object>
<Type>pointer</Type>
<Scope></Scope>
<IOProtocol>m_axi</IOProtocol>
<IOConfig></IOConfig>
<Dir>in</Dir>
<Bits>1</Bits>
<Attribute>unknown</Attribute>
</RtlPorts>
<RtlPorts>
<name>m_axi_gmem1_0_BUSER</name>
<Object>gmem1</Object>
<Type>pointer</Type>
<Scope></Scope>
<IOProtocol>m_axi</IOProtocol>
<IOConfig></IOConfig>
<Dir>in</Dir>
<Bits>1</Bits>
<Attribute>unknown</Attribute>
</RtlPorts>
<RtlPorts>
<name>sext_ln280</name>
<Object>sext_ln280</Object>
<Type>scalar</Type>
<Scope></Scope>
<IOProtocol>ap_none</IOProtocol>
<IOConfig></IOConfig>
<Dir>in</Dir>
<Bits>62</Bits>
<Attribute>data</Attribute>
</RtlPorts>
<RtlPorts>
<name>p_ZZ10top_kernelPA256_K8ap_fixedILi24ELi8EL9ap_q_mode0EL9ap_o_mode0ELi0EEPA256_S2_89_address0</name>
<Object>p_ZZ10top_kernelPA256_K8ap_fixedILi24ELi8EL9ap_q_mode0EL9ap_o_mode0ELi0EEPA256_S2_89</Object>
<Type>array</Type>
<Scope>global</Scope>
<IOProtocol>ap_memory</IOProtocol>
<IOConfig></IOConfig>
<Dir>out</Dir>
<Bits>11</Bits>
<Attribute>address</Attribute>
</RtlPorts>
<RtlPorts>
<name>p_ZZ10top_kernelPA256_K8ap_fixedILi24ELi8EL9ap_q_mode0EL9ap_o_mode0ELi0EEPA256_S2_89_ce0</name>
<Object>p_ZZ10top_kernelPA256_K8ap_fixedILi24ELi8EL9ap_q_mode0EL9ap_o_mode0ELi0EEPA256_S2_89</Object>
<Type>array</Type>
<Scope>global</Scope>
<IOProtocol>ap_memory</IOProtocol>
<IOConfig></IOConfig>
<Dir>out</Dir>
<Bits>1</Bits>
<Attribute>control</Attribute>
</RtlPorts>
<RtlPorts>
<name>p_ZZ10top_kernelPA256_K8ap_fixedILi24ELi8EL9ap_q_mode0EL9ap_o_mode0ELi0EEPA256_S2_89_q0</name>
<Object>p_ZZ10top_kernelPA256_K8ap_fixedILi24ELi8EL9ap_q_mode0EL9ap_o_mode0ELi0EEPA256_S2_89</Object>
<Type>array</Type>
<Scope>global</Scope>
<IOProtocol>ap_memory</IOProtocol>
<IOConfig></IOConfig>
<Dir>in</Dir>
<Bits>24</Bits>
<Attribute>data</Attribute>
</RtlPorts>
<RtlPorts>
<name>p_ZZ10top_kernelPA256_K8ap_fixedILi24ELi8EL9ap_q_mode0EL9ap_o_mode0ELi0EEPA256_S2_88_address0</name>
<Object>p_ZZ10top_kernelPA256_K8ap_fixedILi24ELi8EL9ap_q_mode0EL9ap_o_mode0ELi0EEPA256_S2_88</Object>
<Type>array</Type>
<Scope>global</Scope>
<IOProtocol>ap_memory</IOProtocol>
<IOConfig></IOConfig>
<Dir>out</Dir>
<Bits>11</Bits>
<Attribute>address</Attribute>
</RtlPorts>
<RtlPorts>
<name>p_ZZ10top_kernelPA256_K8ap_fixedILi24ELi8EL9ap_q_mode0EL9ap_o_mode0ELi0EEPA256_S2_88_ce0</name>
<Object>p_ZZ10top_kernelPA256_K8ap_fixedILi24ELi8EL9ap_q_mode0EL9ap_o_mode0ELi0EEPA256_S2_88</Object>
<Type>array</Type>
<Scope>global</Scope>
<IOProtocol>ap_memory</IOProtocol>
<IOConfig></IOConfig>
<Dir>out</Dir>
<Bits>1</Bits>
<Attribute>control</Attribute>
</RtlPorts>
<RtlPorts>
<name>p_ZZ10top_kernelPA256_K8ap_fixedILi24ELi8EL9ap_q_mode0EL9ap_o_mode0ELi0EEPA256_S2_88_q0</name>
<Object>p_ZZ10top_kernelPA256_K8ap_fixedILi24ELi8EL9ap_q_mode0EL9ap_o_mode0ELi0EEPA256_S2_88</Object>
<Type>array</Type>
<Scope>global</Scope>
<IOProtocol>ap_memory</IOProtocol>
<IOConfig></IOConfig>
<Dir>in</Dir>
<Bits>24</Bits>
<Attribute>data</Attribute>
</RtlPorts>
<RtlPorts>
<name>p_ZZ10top_kernelPA256_K8ap_fixedILi24ELi8EL9ap_q_mode0EL9ap_o_mode0ELi0EEPA256_S2_87_address0</name>
<Object>p_ZZ10top_kernelPA256_K8ap_fixedILi24ELi8EL9ap_q_mode0EL9ap_o_mode0ELi0EEPA256_S2_87</Object>
<Type>array</Type>
<Scope>global</Scope>
<IOProtocol>ap_memory</IOProtocol>
<IOConfig></IOConfig>
<Dir>out</Dir>
<Bits>11</Bits>
<Attribute>address</Attribute>
</RtlPorts>
<RtlPorts>
<name>p_ZZ10top_kernelPA256_K8ap_fixedILi24ELi8EL9ap_q_mode0EL9ap_o_mode0ELi0EEPA256_S2_87_ce0</name>
<Object>p_ZZ10top_kernelPA256_K8ap_fixedILi24ELi8EL9ap_q_mode0EL9ap_o_mode0ELi0EEPA256_S2_87</Object>
<Type>array</Type>
<Scope>global</Scope>
<IOProtocol>ap_memory</IOProtocol>
<IOConfig></IOConfig>
<Dir>out</Dir>
<Bits>1</Bits>
<Attribute>control</Attribute>
</RtlPorts>
<RtlPorts>
<name>p_ZZ10top_kernelPA256_K8ap_fixedILi24ELi8EL9ap_q_mode0EL9ap_o_mode0ELi0EEPA256_S2_87_q0</name>
<Object>p_ZZ10top_kernelPA256_K8ap_fixedILi24ELi8EL9ap_q_mode0EL9ap_o_mode0ELi0EEPA256_S2_87</Object>
<Type>array</Type>
<Scope>global</Scope>
<IOProtocol>ap_memory</IOProtocol>
<IOConfig></IOConfig>
<Dir>in</Dir>
<Bits>24</Bits>
<Attribute>data</Attribute>
</RtlPorts>
<RtlPorts>
<name>p_ZZ10top_kernelPA256_K8ap_fixedILi24ELi8EL9ap_q_mode0EL9ap_o_mode0ELi0EEPA256_S2_71_address0</name>
<Object>p_ZZ10top_kernelPA256_K8ap_fixedILi24ELi8EL9ap_q_mode0EL9ap_o_mode0ELi0EEPA256_S2_71</Object>
<Type>array</Type>
<Scope>global</Scope>
<IOProtocol>ap_memory</IOProtocol>
<IOConfig></IOConfig>
<Dir>out</Dir>
<Bits>11</Bits>
<Attribute>address</Attribute>
</RtlPorts>
<RtlPorts>
<name>p_ZZ10top_kernelPA256_K8ap_fixedILi24ELi8EL9ap_q_mode0EL9ap_o_mode0ELi0EEPA256_S2_71_ce0</name>
<Object>p_ZZ10top_kernelPA256_K8ap_fixedILi24ELi8EL9ap_q_mode0EL9ap_o_mode0ELi0EEPA256_S2_71</Object>
<Type>array</Type>
<Scope>global</Scope>
<IOProtocol>ap_memory</IOProtocol>
<IOConfig></IOConfig>
<Dir>out</Dir>
<Bits>1</Bits>
<Attribute>control</Attribute>
</RtlPorts>
<RtlPorts>
<name>p_ZZ10top_kernelPA256_K8ap_fixedILi24ELi8EL9ap_q_mode0EL9ap_o_mode0ELi0EEPA256_S2_71_q0</name>
<Object>p_ZZ10top_kernelPA256_K8ap_fixedILi24ELi8EL9ap_q_mode0EL9ap_o_mode0ELi0EEPA256_S2_71</Object>
<Type>array</Type>
<Scope>global</Scope>
<IOProtocol>ap_memory</IOProtocol>
<IOConfig></IOConfig>
<Dir>in</Dir>
<Bits>24</Bits>
<Attribute>data</Attribute>
</RtlPorts>
<RtlPorts>
<name>p_ZZ10top_kernelPA256_K8ap_fixedILi24ELi8EL9ap_q_mode0EL9ap_o_mode0ELi0EEPA256_S2_70_address0</name>
<Object>p_ZZ10top_kernelPA256_K8ap_fixedILi24ELi8EL9ap_q_mode0EL9ap_o_mode0ELi0EEPA256_S2_70</Object>
<Type>array</Type>
<Scope>global</Scope>
<IOProtocol>ap_memory</IOProtocol>
<IOConfig></IOConfig>
<Dir>out</Dir>
<Bits>11</Bits>
<Attribute>address</Attribute>
</RtlPorts>
<RtlPorts>
<name>p_ZZ10top_kernelPA256_K8ap_fixedILi24ELi8EL9ap_q_mode0EL9ap_o_mode0ELi0EEPA256_S2_70_ce0</name>
<Object>p_ZZ10top_kernelPA256_K8ap_fixedILi24ELi8EL9ap_q_mode0EL9ap_o_mode0ELi0EEPA256_S2_70</Object>
<Type>array</Type>
<Scope>global</Scope>
<IOProtocol>ap_memory</IOProtocol>
<IOConfig></IOConfig>
<Dir>out</Dir>
<Bits>1</Bits>
<Attribute>control</Attribute>
</RtlPorts>
<RtlPorts>
<name>p_ZZ10top_kernelPA256_K8ap_fixedILi24ELi8EL9ap_q_mode0EL9ap_o_mode0ELi0EEPA256_S2_70_q0</name>
<Object>p_ZZ10top_kernelPA256_K8ap_fixedILi24ELi8EL9ap_q_mode0EL9ap_o_mode0ELi0EEPA256_S2_70</Object>
<Type>array</Type>
<Scope>global</Scope>
<IOProtocol>ap_memory</IOProtocol>
<IOConfig></IOConfig>
<Dir>in</Dir>
<Bits>24</Bits>
<Attribute>data</Attribute>
</RtlPorts>
<RtlPorts>
<name>p_ZZ10top_kernelPA256_K8ap_fixedILi24ELi8EL9ap_q_mode0EL9ap_o_mode0ELi0EEPA256_S2_69_address0</name>
<Object>p_ZZ10top_kernelPA256_K8ap_fixedILi24ELi8EL9ap_q_mode0EL9ap_o_mode0ELi0EEPA256_S2_69</Object>
<Type>array</Type>
<Scope>global</Scope>
<IOProtocol>ap_memory</IOProtocol>
<IOConfig></IOConfig>
<Dir>out</Dir>
<Bits>11</Bits>
<Attribute>address</Attribute>
</RtlPorts>
<RtlPorts>
<name>p_ZZ10top_kernelPA256_K8ap_fixedILi24ELi8EL9ap_q_mode0EL9ap_o_mode0ELi0EEPA256_S2_69_ce0</name>
<Object>p_ZZ10top_kernelPA256_K8ap_fixedILi24ELi8EL9ap_q_mode0EL9ap_o_mode0ELi0EEPA256_S2_69</Object>
<Type>array</Type>
<Scope>global</Scope>
<IOProtocol>ap_memory</IOProtocol>
<IOConfig></IOConfig>
<Dir>out</Dir>
<Bits>1</Bits>
<Attribute>control</Attribute>
</RtlPorts>
<RtlPorts>
<name>p_ZZ10top_kernelPA256_K8ap_fixedILi24ELi8EL9ap_q_mode0EL9ap_o_mode0ELi0EEPA256_S2_69_q0</name>
<Object>p_ZZ10top_kernelPA256_K8ap_fixedILi24ELi8EL9ap_q_mode0EL9ap_o_mode0ELi0EEPA256_S2_69</Object>
<Type>array</Type>
<Scope>global</Scope>
<IOProtocol>ap_memory</IOProtocol>
<IOConfig></IOConfig>
<Dir>in</Dir>
<Bits>24</Bits>
<Attribute>data</Attribute>
</RtlPorts>
<RtlPorts>
<name>p_ZZ10top_kernelPA256_K8ap_fixedILi24ELi8EL9ap_q_mode0EL9ap_o_mode0ELi0EEPA256_S2_68_address0</name>
<Object>p_ZZ10top_kernelPA256_K8ap_fixedILi24ELi8EL9ap_q_mode0EL9ap_o_mode0ELi0EEPA256_S2_68</Object>
<Type>array</Type>
<Scope>global</Scope>
<IOProtocol>ap_memory</IOProtocol>
<IOConfig></IOConfig>
<Dir>out</Dir>
<Bits>11</Bits>
<Attribute>address</Attribute>
</RtlPorts>
<RtlPorts>
<name>p_ZZ10top_kernelPA256_K8ap_fixedILi24ELi8EL9ap_q_mode0EL9ap_o_mode0ELi0EEPA256_S2_68_ce0</name>
<Object>p_ZZ10top_kernelPA256_K8ap_fixedILi24ELi8EL9ap_q_mode0EL9ap_o_mode0ELi0EEPA256_S2_68</Object>
<Type>array</Type>
<Scope>global</Scope>
<IOProtocol>ap_memory</IOProtocol>
<IOConfig></IOConfig>
<Dir>out</Dir>
<Bits>1</Bits>
<Attribute>control</Attribute>
</RtlPorts>
<RtlPorts>
<name>p_ZZ10top_kernelPA256_K8ap_fixedILi24ELi8EL9ap_q_mode0EL9ap_o_mode0ELi0EEPA256_S2_68_q0</name>
<Object>p_ZZ10top_kernelPA256_K8ap_fixedILi24ELi8EL9ap_q_mode0EL9ap_o_mode0ELi0EEPA256_S2_68</Object>
<Type>array</Type>
<Scope>global</Scope>
<IOProtocol>ap_memory</IOProtocol>
<IOConfig></IOConfig>
<Dir>in</Dir>
<Bits>24</Bits>
<Attribute>data</Attribute>
</RtlPorts>
<RtlPorts>
<name>p_ZZ10top_kernelPA256_K8ap_fixedILi24ELi8EL9ap_q_mode0EL9ap_o_mode0ELi0EEPA256_S2_67_address0</name>
<Object>p_ZZ10top_kernelPA256_K8ap_fixedILi24ELi8EL9ap_q_mode0EL9ap_o_mode0ELi0EEPA256_S2_67</Object>
<Type>array</Type>
<Scope>global</Scope>
<IOProtocol>ap_memory</IOProtocol>
<IOConfig></IOConfig>
<Dir>out</Dir>
<Bits>11</Bits>
<Attribute>address</Attribute>
</RtlPorts>
<RtlPorts>
<name>p_ZZ10top_kernelPA256_K8ap_fixedILi24ELi8EL9ap_q_mode0EL9ap_o_mode0ELi0EEPA256_S2_67_ce0</name>
<Object>p_ZZ10top_kernelPA256_K8ap_fixedILi24ELi8EL9ap_q_mode0EL9ap_o_mode0ELi0EEPA256_S2_67</Object>
<Type>array</Type>
<Scope>global</Scope>
<IOProtocol>ap_memory</IOProtocol>
<IOConfig></IOConfig>
<Dir>out</Dir>
<Bits>1</Bits>
<Attribute>control</Attribute>
</RtlPorts>
<RtlPorts>
<name>p_ZZ10top_kernelPA256_K8ap_fixedILi24ELi8EL9ap_q_mode0EL9ap_o_mode0ELi0EEPA256_S2_67_q0</name>
<Object>p_ZZ10top_kernelPA256_K8ap_fixedILi24ELi8EL9ap_q_mode0EL9ap_o_mode0ELi0EEPA256_S2_67</Object>
<Type>array</Type>
<Scope>global</Scope>
<IOProtocol>ap_memory</IOProtocol>
<IOConfig></IOConfig>
<Dir>in</Dir>
<Bits>24</Bits>
<Attribute>data</Attribute>
</RtlPorts>
<RtlPorts>
<name>p_ZZ10top_kernelPA256_K8ap_fixedILi24ELi8EL9ap_q_mode0EL9ap_o_mode0ELi0EEPA256_S2_66_address0</name>
<Object>p_ZZ10top_kernelPA256_K8ap_fixedILi24ELi8EL9ap_q_mode0EL9ap_o_mode0ELi0EEPA256_S2_66</Object>
<Type>array</Type>
<Scope>global</Scope>
<IOProtocol>ap_memory</IOProtocol>
<IOConfig></IOConfig>
<Dir>out</Dir>
<Bits>11</Bits>
<Attribute>address</Attribute>
</RtlPorts>
<RtlPorts>
<name>p_ZZ10top_kernelPA256_K8ap_fixedILi24ELi8EL9ap_q_mode0EL9ap_o_mode0ELi0EEPA256_S2_66_ce0</name>
<Object>p_ZZ10top_kernelPA256_K8ap_fixedILi24ELi8EL9ap_q_mode0EL9ap_o_mode0ELi0EEPA256_S2_66</Object>
<Type>array</Type>
<Scope>global</Scope>
<IOProtocol>ap_memory</IOProtocol>
<IOConfig></IOConfig>
<Dir>out</Dir>
<Bits>1</Bits>
<Attribute>control</Attribute>
</RtlPorts>
<RtlPorts>
<name>p_ZZ10top_kernelPA256_K8ap_fixedILi24ELi8EL9ap_q_mode0EL9ap_o_mode0ELi0EEPA256_S2_66_q0</name>
<Object>p_ZZ10top_kernelPA256_K8ap_fixedILi24ELi8EL9ap_q_mode0EL9ap_o_mode0ELi0EEPA256_S2_66</Object>
<Type>array</Type>
<Scope>global</Scope>
<IOProtocol>ap_memory</IOProtocol>
<IOConfig></IOConfig>
<Dir>in</Dir>
<Bits>24</Bits>
<Attribute>data</Attribute>
</RtlPorts>
<RtlPorts>
<name>p_ZZ10top_kernelPA256_K8ap_fixedILi24ELi8EL9ap_q_mode0EL9ap_o_mode0ELi0EEPA256_S2_65_address0</name>
<Object>p_ZZ10top_kernelPA256_K8ap_fixedILi24ELi8EL9ap_q_mode0EL9ap_o_mode0ELi0EEPA256_S2_65</Object>
<Type>array</Type>
<Scope>global</Scope>
<IOProtocol>ap_memory</IOProtocol>
<IOConfig></IOConfig>
<Dir>out</Dir>
<Bits>11</Bits>
<Attribute>address</Attribute>
</RtlPorts>
<RtlPorts>
<name>p_ZZ10top_kernelPA256_K8ap_fixedILi24ELi8EL9ap_q_mode0EL9ap_o_mode0ELi0EEPA256_S2_65_ce0</name>
<Object>p_ZZ10top_kernelPA256_K8ap_fixedILi24ELi8EL9ap_q_mode0EL9ap_o_mode0ELi0EEPA256_S2_65</Object>
<Type>array</Type>
<Scope>global</Scope>
<IOProtocol>ap_memory</IOProtocol>
<IOConfig></IOConfig>
<Dir>out</Dir>
<Bits>1</Bits>
<Attribute>control</Attribute>
</RtlPorts>
<RtlPorts>
<name>p_ZZ10top_kernelPA256_K8ap_fixedILi24ELi8EL9ap_q_mode0EL9ap_o_mode0ELi0EEPA256_S2_65_q0</name>
<Object>p_ZZ10top_kernelPA256_K8ap_fixedILi24ELi8EL9ap_q_mode0EL9ap_o_mode0ELi0EEPA256_S2_65</Object>
<Type>array</Type>
<Scope>global</Scope>
<IOProtocol>ap_memory</IOProtocol>
<IOConfig></IOConfig>
<Dir>in</Dir>
<Bits>24</Bits>
<Attribute>data</Attribute>
</RtlPorts>
<RtlPorts>
<name>p_ZZ10top_kernelPA256_K8ap_fixedILi24ELi8EL9ap_q_mode0EL9ap_o_mode0ELi0EEPA256_S2_64_address0</name>
<Object>p_ZZ10top_kernelPA256_K8ap_fixedILi24ELi8EL9ap_q_mode0EL9ap_o_mode0ELi0EEPA256_S2_64</Object>
<Type>array</Type>
<Scope>global</Scope>
<IOProtocol>ap_memory</IOProtocol>
<IOConfig></IOConfig>
<Dir>out</Dir>
<Bits>11</Bits>
<Attribute>address</Attribute>
</RtlPorts>
<RtlPorts>
<name>p_ZZ10top_kernelPA256_K8ap_fixedILi24ELi8EL9ap_q_mode0EL9ap_o_mode0ELi0EEPA256_S2_64_ce0</name>
<Object>p_ZZ10top_kernelPA256_K8ap_fixedILi24ELi8EL9ap_q_mode0EL9ap_o_mode0ELi0EEPA256_S2_64</Object>
<Type>array</Type>
<Scope>global</Scope>
<IOProtocol>ap_memory</IOProtocol>
<IOConfig></IOConfig>
<Dir>out</Dir>
<Bits>1</Bits>
<Attribute>control</Attribute>
</RtlPorts>
<RtlPorts>
<name>p_ZZ10top_kernelPA256_K8ap_fixedILi24ELi8EL9ap_q_mode0EL9ap_o_mode0ELi0EEPA256_S2_64_q0</name>
<Object>p_ZZ10top_kernelPA256_K8ap_fixedILi24ELi8EL9ap_q_mode0EL9ap_o_mode0ELi0EEPA256_S2_64</Object>
<Type>array</Type>
<Scope>global</Scope>
<IOProtocol>ap_memory</IOProtocol>
<IOConfig></IOConfig>
<Dir>in</Dir>
<Bits>24</Bits>
<Attribute>data</Attribute>
</RtlPorts>
<RtlPorts>
<name>p_ZZ10top_kernelPA256_K8ap_fixedILi24ELi8EL9ap_q_mode0EL9ap_o_mode0ELi0EEPA256_S2_63_address0</name>
<Object>p_ZZ10top_kernelPA256_K8ap_fixedILi24ELi8EL9ap_q_mode0EL9ap_o_mode0ELi0EEPA256_S2_63</Object>
<Type>array</Type>
<Scope>global</Scope>
<IOProtocol>ap_memory</IOProtocol>
<IOConfig></IOConfig>
<Dir>out</Dir>
<Bits>11</Bits>
<Attribute>address</Attribute>
</RtlPorts>
<RtlPorts>
<name>p_ZZ10top_kernelPA256_K8ap_fixedILi24ELi8EL9ap_q_mode0EL9ap_o_mode0ELi0EEPA256_S2_63_ce0</name>
<Object>p_ZZ10top_kernelPA256_K8ap_fixedILi24ELi8EL9ap_q_mode0EL9ap_o_mode0ELi0EEPA256_S2_63</Object>
<Type>array</Type>
<Scope>global</Scope>
<IOProtocol>ap_memory</IOProtocol>
<IOConfig></IOConfig>
<Dir>out</Dir>
<Bits>1</Bits>
<Attribute>control</Attribute>
</RtlPorts>
<RtlPorts>
<name>p_ZZ10top_kernelPA256_K8ap_fixedILi24ELi8EL9ap_q_mode0EL9ap_o_mode0ELi0EEPA256_S2_63_q0</name>
<Object>p_ZZ10top_kernelPA256_K8ap_fixedILi24ELi8EL9ap_q_mode0EL9ap_o_mode0ELi0EEPA256_S2_63</Object>
<Type>array</Type>
<Scope>global</Scope>
<IOProtocol>ap_memory</IOProtocol>
<IOConfig></IOConfig>
<Dir>in</Dir>
<Bits>24</Bits>
<Attribute>data</Attribute>
</RtlPorts>
<RtlPorts>
<name>p_ZZ10top_kernelPA256_K8ap_fixedILi24ELi8EL9ap_q_mode0EL9ap_o_mode0ELi0EEPA256_S2_62_address0</name>
<Object>p_ZZ10top_kernelPA256_K8ap_fixedILi24ELi8EL9ap_q_mode0EL9ap_o_mode0ELi0EEPA256_S2_62</Object>
<Type>array</Type>
<Scope>global</Scope>
<IOProtocol>ap_memory</IOProtocol>
<IOConfig></IOConfig>
<Dir>out</Dir>
<Bits>11</Bits>
<Attribute>address</Attribute>
</RtlPorts>
<RtlPorts>
<name>p_ZZ10top_kernelPA256_K8ap_fixedILi24ELi8EL9ap_q_mode0EL9ap_o_mode0ELi0EEPA256_S2_62_ce0</name>
<Object>p_ZZ10top_kernelPA256_K8ap_fixedILi24ELi8EL9ap_q_mode0EL9ap_o_mode0ELi0EEPA256_S2_62</Object>
<Type>array</Type>
<Scope>global</Scope>
<IOProtocol>ap_memory</IOProtocol>
<IOConfig></IOConfig>
<Dir>out</Dir>
<Bits>1</Bits>
<Attribute>control</Attribute>
</RtlPorts>
<RtlPorts>
<name>p_ZZ10top_kernelPA256_K8ap_fixedILi24ELi8EL9ap_q_mode0EL9ap_o_mode0ELi0EEPA256_S2_62_q0</name>
<Object>p_ZZ10top_kernelPA256_K8ap_fixedILi24ELi8EL9ap_q_mode0EL9ap_o_mode0ELi0EEPA256_S2_62</Object>
<Type>array</Type>
<Scope>global</Scope>
<IOProtocol>ap_memory</IOProtocol>
<IOConfig></IOConfig>
<Dir>in</Dir>
<Bits>24</Bits>
<Attribute>data</Attribute>
</RtlPorts>
<RtlPorts>
<name>p_ZZ10top_kernelPA256_K8ap_fixedILi24ELi8EL9ap_q_mode0EL9ap_o_mode0ELi0EEPA256_S2_61_address0</name>
<Object>p_ZZ10top_kernelPA256_K8ap_fixedILi24ELi8EL9ap_q_mode0EL9ap_o_mode0ELi0EEPA256_S2_61</Object>
<Type>array</Type>
<Scope>global</Scope>
<IOProtocol>ap_memory</IOProtocol>
<IOConfig></IOConfig>
<Dir>out</Dir>
<Bits>11</Bits>
<Attribute>address</Attribute>
</RtlPorts>
<RtlPorts>
<name>p_ZZ10top_kernelPA256_K8ap_fixedILi24ELi8EL9ap_q_mode0EL9ap_o_mode0ELi0EEPA256_S2_61_ce0</name>
<Object>p_ZZ10top_kernelPA256_K8ap_fixedILi24ELi8EL9ap_q_mode0EL9ap_o_mode0ELi0EEPA256_S2_61</Object>
<Type>array</Type>
<Scope>global</Scope>
<IOProtocol>ap_memory</IOProtocol>
<IOConfig></IOConfig>
<Dir>out</Dir>
<Bits>1</Bits>
<Attribute>control</Attribute>
</RtlPorts>
<RtlPorts>
<name>p_ZZ10top_kernelPA256_K8ap_fixedILi24ELi8EL9ap_q_mode0EL9ap_o_mode0ELi0EEPA256_S2_61_q0</name>
<Object>p_ZZ10top_kernelPA256_K8ap_fixedILi24ELi8EL9ap_q_mode0EL9ap_o_mode0ELi0EEPA256_S2_61</Object>
<Type>array</Type>
<Scope>global</Scope>
<IOProtocol>ap_memory</IOProtocol>
<IOConfig></IOConfig>
<Dir>in</Dir>
<Bits>24</Bits>
<Attribute>data</Attribute>
</RtlPorts>
<RtlPorts>
<name>p_ZZ10top_kernelPA256_K8ap_fixedILi24ELi8EL9ap_q_mode0EL9ap_o_mode0ELi0EEPA256_S2_60_address0</name>
<Object>p_ZZ10top_kernelPA256_K8ap_fixedILi24ELi8EL9ap_q_mode0EL9ap_o_mode0ELi0EEPA256_S2_60</Object>
<Type>array</Type>
<Scope>global</Scope>
<IOProtocol>ap_memory</IOProtocol>
<IOConfig></IOConfig>
<Dir>out</Dir>
<Bits>11</Bits>
<Attribute>address</Attribute>
</RtlPorts>
<RtlPorts>
<name>p_ZZ10top_kernelPA256_K8ap_fixedILi24ELi8EL9ap_q_mode0EL9ap_o_mode0ELi0EEPA256_S2_60_ce0</name>
<Object>p_ZZ10top_kernelPA256_K8ap_fixedILi24ELi8EL9ap_q_mode0EL9ap_o_mode0ELi0EEPA256_S2_60</Object>
<Type>array</Type>
<Scope>global</Scope>
<IOProtocol>ap_memory</IOProtocol>
<IOConfig></IOConfig>
<Dir>out</Dir>
<Bits>1</Bits>
<Attribute>control</Attribute>
</RtlPorts>
<RtlPorts>
<name>p_ZZ10top_kernelPA256_K8ap_fixedILi24ELi8EL9ap_q_mode0EL9ap_o_mode0ELi0EEPA256_S2_60_q0</name>
<Object>p_ZZ10top_kernelPA256_K8ap_fixedILi24ELi8EL9ap_q_mode0EL9ap_o_mode0ELi0EEPA256_S2_60</Object>
<Type>array</Type>
<Scope>global</Scope>
<IOProtocol>ap_memory</IOProtocol>
<IOConfig></IOConfig>
<Dir>in</Dir>
<Bits>24</Bits>
<Attribute>data</Attribute>
</RtlPorts>
<RtlPorts>
<name>p_ZZ10top_kernelPA256_K8ap_fixedILi24ELi8EL9ap_q_mode0EL9ap_o_mode0ELi0EEPA256_S2_59_address0</name>
<Object>p_ZZ10top_kernelPA256_K8ap_fixedILi24ELi8EL9ap_q_mode0EL9ap_o_mode0ELi0EEPA256_S2_59</Object>
<Type>array</Type>
<Scope>global</Scope>
<IOProtocol>ap_memory</IOProtocol>
<IOConfig></IOConfig>
<Dir>out</Dir>
<Bits>11</Bits>
<Attribute>address</Attribute>
</RtlPorts>
<RtlPorts>
<name>p_ZZ10top_kernelPA256_K8ap_fixedILi24ELi8EL9ap_q_mode0EL9ap_o_mode0ELi0EEPA256_S2_59_ce0</name>
<Object>p_ZZ10top_kernelPA256_K8ap_fixedILi24ELi8EL9ap_q_mode0EL9ap_o_mode0ELi0EEPA256_S2_59</Object>
<Type>array</Type>
<Scope>global</Scope>
<IOProtocol>ap_memory</IOProtocol>
<IOConfig></IOConfig>
<Dir>out</Dir>
<Bits>1</Bits>
<Attribute>control</Attribute>
</RtlPorts>
<RtlPorts>
<name>p_ZZ10top_kernelPA256_K8ap_fixedILi24ELi8EL9ap_q_mode0EL9ap_o_mode0ELi0EEPA256_S2_59_q0</name>
<Object>p_ZZ10top_kernelPA256_K8ap_fixedILi24ELi8EL9ap_q_mode0EL9ap_o_mode0ELi0EEPA256_S2_59</Object>
<Type>array</Type>
<Scope>global</Scope>
<IOProtocol>ap_memory</IOProtocol>
<IOConfig></IOConfig>
<Dir>in</Dir>
<Bits>24</Bits>
<Attribute>data</Attribute>
</RtlPorts>
<RtlPorts>
<name>p_ZZ10top_kernelPA256_K8ap_fixedILi24ELi8EL9ap_q_mode0EL9ap_o_mode0ELi0EEPA256_S2_58_address0</name>
<Object>p_ZZ10top_kernelPA256_K8ap_fixedILi24ELi8EL9ap_q_mode0EL9ap_o_mode0ELi0EEPA256_S2_58</Object>
<Type>array</Type>
<Scope>global</Scope>
<IOProtocol>ap_memory</IOProtocol>
<IOConfig></IOConfig>
<Dir>out</Dir>
<Bits>11</Bits>
<Attribute>address</Attribute>
</RtlPorts>
<RtlPorts>
<name>p_ZZ10top_kernelPA256_K8ap_fixedILi24ELi8EL9ap_q_mode0EL9ap_o_mode0ELi0EEPA256_S2_58_ce0</name>
<Object>p_ZZ10top_kernelPA256_K8ap_fixedILi24ELi8EL9ap_q_mode0EL9ap_o_mode0ELi0EEPA256_S2_58</Object>
<Type>array</Type>
<Scope>global</Scope>
<IOProtocol>ap_memory</IOProtocol>
<IOConfig></IOConfig>
<Dir>out</Dir>
<Bits>1</Bits>
<Attribute>control</Attribute>
</RtlPorts>
<RtlPorts>
<name>p_ZZ10top_kernelPA256_K8ap_fixedILi24ELi8EL9ap_q_mode0EL9ap_o_mode0ELi0EEPA256_S2_58_q0</name>
<Object>p_ZZ10top_kernelPA256_K8ap_fixedILi24ELi8EL9ap_q_mode0EL9ap_o_mode0ELi0EEPA256_S2_58</Object>
<Type>array</Type>
<Scope>global</Scope>
<IOProtocol>ap_memory</IOProtocol>
<IOConfig></IOConfig>
<Dir>in</Dir>
<Bits>24</Bits>
<Attribute>data</Attribute>
</RtlPorts>
<RtlPorts>
<name>p_ZZ10top_kernelPA256_K8ap_fixedILi24ELi8EL9ap_q_mode0EL9ap_o_mode0ELi0EEPA256_S2_57_address0</name>
<Object>p_ZZ10top_kernelPA256_K8ap_fixedILi24ELi8EL9ap_q_mode0EL9ap_o_mode0ELi0EEPA256_S2_57</Object>
<Type>array</Type>
<Scope>global</Scope>
<IOProtocol>ap_memory</IOProtocol>
<IOConfig></IOConfig>
<Dir>out</Dir>
<Bits>11</Bits>
<Attribute>address</Attribute>
</RtlPorts>
<RtlPorts>
<name>p_ZZ10top_kernelPA256_K8ap_fixedILi24ELi8EL9ap_q_mode0EL9ap_o_mode0ELi0EEPA256_S2_57_ce0</name>
<Object>p_ZZ10top_kernelPA256_K8ap_fixedILi24ELi8EL9ap_q_mode0EL9ap_o_mode0ELi0EEPA256_S2_57</Object>
<Type>array</Type>
<Scope>global</Scope>
<IOProtocol>ap_memory</IOProtocol>
<IOConfig></IOConfig>
<Dir>out</Dir>
<Bits>1</Bits>
<Attribute>control</Attribute>
</RtlPorts>
<RtlPorts>
<name>p_ZZ10top_kernelPA256_K8ap_fixedILi24ELi8EL9ap_q_mode0EL9ap_o_mode0ELi0EEPA256_S2_57_q0</name>
<Object>p_ZZ10top_kernelPA256_K8ap_fixedILi24ELi8EL9ap_q_mode0EL9ap_o_mode0ELi0EEPA256_S2_57</Object>
<Type>array</Type>
<Scope>global</Scope>
<IOProtocol>ap_memory</IOProtocol>
<IOConfig></IOConfig>
<Dir>in</Dir>
<Bits>24</Bits>
<Attribute>data</Attribute>
</RtlPorts>
<RtlPorts>
<name>p_ZZ10top_kernelPA256_K8ap_fixedILi24ELi8EL9ap_q_mode0EL9ap_o_mode0ELi0EEPA256_S2_56_address0</name>
<Object>p_ZZ10top_kernelPA256_K8ap_fixedILi24ELi8EL9ap_q_mode0EL9ap_o_mode0ELi0EEPA256_S2_56</Object>
<Type>array</Type>
<Scope>global</Scope>
<IOProtocol>ap_memory</IOProtocol>
<IOConfig></IOConfig>
<Dir>out</Dir>
<Bits>11</Bits>
<Attribute>address</Attribute>
</RtlPorts>
<RtlPorts>
<name>p_ZZ10top_kernelPA256_K8ap_fixedILi24ELi8EL9ap_q_mode0EL9ap_o_mode0ELi0EEPA256_S2_56_ce0</name>
<Object>p_ZZ10top_kernelPA256_K8ap_fixedILi24ELi8EL9ap_q_mode0EL9ap_o_mode0ELi0EEPA256_S2_56</Object>
<Type>array</Type>
<Scope>global</Scope>
<IOProtocol>ap_memory</IOProtocol>
<IOConfig></IOConfig>
<Dir>out</Dir>
<Bits>1</Bits>
<Attribute>control</Attribute>
</RtlPorts>
<RtlPorts>
<name>p_ZZ10top_kernelPA256_K8ap_fixedILi24ELi8EL9ap_q_mode0EL9ap_o_mode0ELi0EEPA256_S2_56_q0</name>
<Object>p_ZZ10top_kernelPA256_K8ap_fixedILi24ELi8EL9ap_q_mode0EL9ap_o_mode0ELi0EEPA256_S2_56</Object>
<Type>array</Type>
<Scope>global</Scope>
<IOProtocol>ap_memory</IOProtocol>
<IOConfig></IOConfig>
<Dir>in</Dir>
<Bits>24</Bits>
<Attribute>data</Attribute>
</RtlPorts>
<RtlPorts>
<name>p_ZZ10top_kernelPA256_K8ap_fixedILi24ELi8EL9ap_q_mode0EL9ap_o_mode0ELi0EEPA256_S2_55_address0</name>
<Object>p_ZZ10top_kernelPA256_K8ap_fixedILi24ELi8EL9ap_q_mode0EL9ap_o_mode0ELi0EEPA256_S2_55</Object>
<Type>array</Type>
<Scope>global</Scope>
<IOProtocol>ap_memory</IOProtocol>
<IOConfig></IOConfig>
<Dir>out</Dir>
<Bits>11</Bits>
<Attribute>address</Attribute>
</RtlPorts>
<RtlPorts>
<name>p_ZZ10top_kernelPA256_K8ap_fixedILi24ELi8EL9ap_q_mode0EL9ap_o_mode0ELi0EEPA256_S2_55_ce0</name>
<Object>p_ZZ10top_kernelPA256_K8ap_fixedILi24ELi8EL9ap_q_mode0EL9ap_o_mode0ELi0EEPA256_S2_55</Object>
<Type>array</Type>
<Scope>global</Scope>
<IOProtocol>ap_memory</IOProtocol>
<IOConfig></IOConfig>
<Dir>out</Dir>
<Bits>1</Bits>
<Attribute>control</Attribute>
</RtlPorts>
<RtlPorts>
<name>p_ZZ10top_kernelPA256_K8ap_fixedILi24ELi8EL9ap_q_mode0EL9ap_o_mode0ELi0EEPA256_S2_55_q0</name>
<Object>p_ZZ10top_kernelPA256_K8ap_fixedILi24ELi8EL9ap_q_mode0EL9ap_o_mode0ELi0EEPA256_S2_55</Object>
<Type>array</Type>
<Scope>global</Scope>
<IOProtocol>ap_memory</IOProtocol>
<IOConfig></IOConfig>
<Dir>in</Dir>
<Bits>24</Bits>
<Attribute>data</Attribute>
</RtlPorts>
<RtlPorts>
<name>p_ZZ10top_kernelPA256_K8ap_fixedILi24ELi8EL9ap_q_mode0EL9ap_o_mode0ELi0EEPA256_S2_54_address0</name>
<Object>p_ZZ10top_kernelPA256_K8ap_fixedILi24ELi8EL9ap_q_mode0EL9ap_o_mode0ELi0EEPA256_S2_54</Object>
<Type>array</Type>
<Scope>global</Scope>
<IOProtocol>ap_memory</IOProtocol>
<IOConfig></IOConfig>
<Dir>out</Dir>
<Bits>11</Bits>
<Attribute>address</Attribute>
</RtlPorts>
<RtlPorts>
<name>p_ZZ10top_kernelPA256_K8ap_fixedILi24ELi8EL9ap_q_mode0EL9ap_o_mode0ELi0EEPA256_S2_54_ce0</name>
<Object>p_ZZ10top_kernelPA256_K8ap_fixedILi24ELi8EL9ap_q_mode0EL9ap_o_mode0ELi0EEPA256_S2_54</Object>
<Type>array</Type>
<Scope>global</Scope>
<IOProtocol>ap_memory</IOProtocol>
<IOConfig></IOConfig>
<Dir>out</Dir>
<Bits>1</Bits>
<Attribute>control</Attribute>
</RtlPorts>
<RtlPorts>
<name>p_ZZ10top_kernelPA256_K8ap_fixedILi24ELi8EL9ap_q_mode0EL9ap_o_mode0ELi0EEPA256_S2_54_q0</name>
<Object>p_ZZ10top_kernelPA256_K8ap_fixedILi24ELi8EL9ap_q_mode0EL9ap_o_mode0ELi0EEPA256_S2_54</Object>
<Type>array</Type>
<Scope>global</Scope>
<IOProtocol>ap_memory</IOProtocol>
<IOConfig></IOConfig>
<Dir>in</Dir>
<Bits>24</Bits>
<Attribute>data</Attribute>
</RtlPorts>
<RtlPorts>
<name>p_ZZ10top_kernelPA256_K8ap_fixedILi24ELi8EL9ap_q_mode0EL9ap_o_mode0ELi0EEPA256_S2_53_address0</name>
<Object>p_ZZ10top_kernelPA256_K8ap_fixedILi24ELi8EL9ap_q_mode0EL9ap_o_mode0ELi0EEPA256_S2_53</Object>
<Type>array</Type>
<Scope>global</Scope>
<IOProtocol>ap_memory</IOProtocol>
<IOConfig></IOConfig>
<Dir>out</Dir>
<Bits>11</Bits>
<Attribute>address</Attribute>
</RtlPorts>
<RtlPorts>
<name>p_ZZ10top_kernelPA256_K8ap_fixedILi24ELi8EL9ap_q_mode0EL9ap_o_mode0ELi0EEPA256_S2_53_ce0</name>
<Object>p_ZZ10top_kernelPA256_K8ap_fixedILi24ELi8EL9ap_q_mode0EL9ap_o_mode0ELi0EEPA256_S2_53</Object>
<Type>array</Type>
<Scope>global</Scope>
<IOProtocol>ap_memory</IOProtocol>
<IOConfig></IOConfig>
<Dir>out</Dir>
<Bits>1</Bits>
<Attribute>control</Attribute>
</RtlPorts>
<RtlPorts>
<name>p_ZZ10top_kernelPA256_K8ap_fixedILi24ELi8EL9ap_q_mode0EL9ap_o_mode0ELi0EEPA256_S2_53_q0</name>
<Object>p_ZZ10top_kernelPA256_K8ap_fixedILi24ELi8EL9ap_q_mode0EL9ap_o_mode0ELi0EEPA256_S2_53</Object>
<Type>array</Type>
<Scope>global</Scope>
<IOProtocol>ap_memory</IOProtocol>
<IOConfig></IOConfig>
<Dir>in</Dir>
<Bits>24</Bits>
<Attribute>data</Attribute>
</RtlPorts>
<RtlPorts>
<name>p_ZZ10top_kernelPA256_K8ap_fixedILi24ELi8EL9ap_q_mode0EL9ap_o_mode0ELi0EEPA256_S2_52_address0</name>
<Object>p_ZZ10top_kernelPA256_K8ap_fixedILi24ELi8EL9ap_q_mode0EL9ap_o_mode0ELi0EEPA256_S2_52</Object>
<Type>array</Type>
<Scope>global</Scope>
<IOProtocol>ap_memory</IOProtocol>
<IOConfig></IOConfig>
<Dir>out</Dir>
<Bits>11</Bits>
<Attribute>address</Attribute>
</RtlPorts>
<RtlPorts>
<name>p_ZZ10top_kernelPA256_K8ap_fixedILi24ELi8EL9ap_q_mode0EL9ap_o_mode0ELi0EEPA256_S2_52_ce0</name>
<Object>p_ZZ10top_kernelPA256_K8ap_fixedILi24ELi8EL9ap_q_mode0EL9ap_o_mode0ELi0EEPA256_S2_52</Object>
<Type>array</Type>
<Scope>global</Scope>
<IOProtocol>ap_memory</IOProtocol>
<IOConfig></IOConfig>
<Dir>out</Dir>
<Bits>1</Bits>
<Attribute>control</Attribute>
</RtlPorts>
<RtlPorts>
<name>p_ZZ10top_kernelPA256_K8ap_fixedILi24ELi8EL9ap_q_mode0EL9ap_o_mode0ELi0EEPA256_S2_52_q0</name>
<Object>p_ZZ10top_kernelPA256_K8ap_fixedILi24ELi8EL9ap_q_mode0EL9ap_o_mode0ELi0EEPA256_S2_52</Object>
<Type>array</Type>
<Scope>global</Scope>
<IOProtocol>ap_memory</IOProtocol>
<IOConfig></IOConfig>
<Dir>in</Dir>
<Bits>24</Bits>
<Attribute>data</Attribute>
</RtlPorts>
<RtlPorts>
<name>p_ZZ10top_kernelPA256_K8ap_fixedILi24ELi8EL9ap_q_mode0EL9ap_o_mode0ELi0EEPA256_S2_51_address0</name>
<Object>p_ZZ10top_kernelPA256_K8ap_fixedILi24ELi8EL9ap_q_mode0EL9ap_o_mode0ELi0EEPA256_S2_51</Object>
<Type>array</Type>
<Scope>global</Scope>
<IOProtocol>ap_memory</IOProtocol>
<IOConfig></IOConfig>
<Dir>out</Dir>
<Bits>11</Bits>
<Attribute>address</Attribute>
</RtlPorts>
<RtlPorts>
<name>p_ZZ10top_kernelPA256_K8ap_fixedILi24ELi8EL9ap_q_mode0EL9ap_o_mode0ELi0EEPA256_S2_51_ce0</name>
<Object>p_ZZ10top_kernelPA256_K8ap_fixedILi24ELi8EL9ap_q_mode0EL9ap_o_mode0ELi0EEPA256_S2_51</Object>
<Type>array</Type>
<Scope>global</Scope>
<IOProtocol>ap_memory</IOProtocol>
<IOConfig></IOConfig>
<Dir>out</Dir>
<Bits>1</Bits>
<Attribute>control</Attribute>
</RtlPorts>
<RtlPorts>
<name>p_ZZ10top_kernelPA256_K8ap_fixedILi24ELi8EL9ap_q_mode0EL9ap_o_mode0ELi0EEPA256_S2_51_q0</name>
<Object>p_ZZ10top_kernelPA256_K8ap_fixedILi24ELi8EL9ap_q_mode0EL9ap_o_mode0ELi0EEPA256_S2_51</Object>
<Type>array</Type>
<Scope>global</Scope>
<IOProtocol>ap_memory</IOProtocol>
<IOConfig></IOConfig>
<Dir>in</Dir>
<Bits>24</Bits>
<Attribute>data</Attribute>
</RtlPorts>
<RtlPorts>
<name>p_ZZ10top_kernelPA256_K8ap_fixedILi24ELi8EL9ap_q_mode0EL9ap_o_mode0ELi0EEPA256_S2_50_address0</name>
<Object>p_ZZ10top_kernelPA256_K8ap_fixedILi24ELi8EL9ap_q_mode0EL9ap_o_mode0ELi0EEPA256_S2_50</Object>
<Type>array</Type>
<Scope>global</Scope>
<IOProtocol>ap_memory</IOProtocol>
<IOConfig></IOConfig>
<Dir>out</Dir>
<Bits>11</Bits>
<Attribute>address</Attribute>
</RtlPorts>
<RtlPorts>
<name>p_ZZ10top_kernelPA256_K8ap_fixedILi24ELi8EL9ap_q_mode0EL9ap_o_mode0ELi0EEPA256_S2_50_ce0</name>
<Object>p_ZZ10top_kernelPA256_K8ap_fixedILi24ELi8EL9ap_q_mode0EL9ap_o_mode0ELi0EEPA256_S2_50</Object>
<Type>array</Type>
<Scope>global</Scope>
<IOProtocol>ap_memory</IOProtocol>
<IOConfig></IOConfig>
<Dir>out</Dir>
<Bits>1</Bits>
<Attribute>control</Attribute>
</RtlPorts>
<RtlPorts>
<name>p_ZZ10top_kernelPA256_K8ap_fixedILi24ELi8EL9ap_q_mode0EL9ap_o_mode0ELi0EEPA256_S2_50_q0</name>
<Object>p_ZZ10top_kernelPA256_K8ap_fixedILi24ELi8EL9ap_q_mode0EL9ap_o_mode0ELi0EEPA256_S2_50</Object>
<Type>array</Type>
<Scope>global</Scope>
<IOProtocol>ap_memory</IOProtocol>
<IOConfig></IOConfig>
<Dir>in</Dir>
<Bits>24</Bits>
<Attribute>data</Attribute>
</RtlPorts>
<RtlPorts>
<name>p_ZZ10top_kernelPA256_K8ap_fixedILi24ELi8EL9ap_q_mode0EL9ap_o_mode0ELi0EEPA256_S2_49_address0</name>
<Object>p_ZZ10top_kernelPA256_K8ap_fixedILi24ELi8EL9ap_q_mode0EL9ap_o_mode0ELi0EEPA256_S2_49</Object>
<Type>array</Type>
<Scope>global</Scope>
<IOProtocol>ap_memory</IOProtocol>
<IOConfig></IOConfig>
<Dir>out</Dir>
<Bits>11</Bits>
<Attribute>address</Attribute>
</RtlPorts>
<RtlPorts>
<name>p_ZZ10top_kernelPA256_K8ap_fixedILi24ELi8EL9ap_q_mode0EL9ap_o_mode0ELi0EEPA256_S2_49_ce0</name>
<Object>p_ZZ10top_kernelPA256_K8ap_fixedILi24ELi8EL9ap_q_mode0EL9ap_o_mode0ELi0EEPA256_S2_49</Object>
<Type>array</Type>
<Scope>global</Scope>
<IOProtocol>ap_memory</IOProtocol>
<IOConfig></IOConfig>
<Dir>out</Dir>
<Bits>1</Bits>
<Attribute>control</Attribute>
</RtlPorts>
<RtlPorts>
<name>p_ZZ10top_kernelPA256_K8ap_fixedILi24ELi8EL9ap_q_mode0EL9ap_o_mode0ELi0EEPA256_S2_49_q0</name>
<Object>p_ZZ10top_kernelPA256_K8ap_fixedILi24ELi8EL9ap_q_mode0EL9ap_o_mode0ELi0EEPA256_S2_49</Object>
<Type>array</Type>
<Scope>global</Scope>
<IOProtocol>ap_memory</IOProtocol>
<IOConfig></IOConfig>
<Dir>in</Dir>
<Bits>24</Bits>
<Attribute>data</Attribute>
</RtlPorts>
<RtlPorts>
<name>p_ZZ10top_kernelPA256_K8ap_fixedILi24ELi8EL9ap_q_mode0EL9ap_o_mode0ELi0EEPA256_S2_48_address0</name>
<Object>p_ZZ10top_kernelPA256_K8ap_fixedILi24ELi8EL9ap_q_mode0EL9ap_o_mode0ELi0EEPA256_S2_48</Object>
<Type>array</Type>
<Scope>global</Scope>
<IOProtocol>ap_memory</IOProtocol>
<IOConfig></IOConfig>
<Dir>out</Dir>
<Bits>11</Bits>
<Attribute>address</Attribute>
</RtlPorts>
<RtlPorts>
<name>p_ZZ10top_kernelPA256_K8ap_fixedILi24ELi8EL9ap_q_mode0EL9ap_o_mode0ELi0EEPA256_S2_48_ce0</name>
<Object>p_ZZ10top_kernelPA256_K8ap_fixedILi24ELi8EL9ap_q_mode0EL9ap_o_mode0ELi0EEPA256_S2_48</Object>
<Type>array</Type>
<Scope>global</Scope>
<IOProtocol>ap_memory</IOProtocol>
<IOConfig></IOConfig>
<Dir>out</Dir>
<Bits>1</Bits>
<Attribute>control</Attribute>
</RtlPorts>
<RtlPorts>
<name>p_ZZ10top_kernelPA256_K8ap_fixedILi24ELi8EL9ap_q_mode0EL9ap_o_mode0ELi0EEPA256_S2_48_q0</name>
<Object>p_ZZ10top_kernelPA256_K8ap_fixedILi24ELi8EL9ap_q_mode0EL9ap_o_mode0ELi0EEPA256_S2_48</Object>
<Type>array</Type>
<Scope>global</Scope>
<IOProtocol>ap_memory</IOProtocol>
<IOConfig></IOConfig>
<Dir>in</Dir>
<Bits>24</Bits>
<Attribute>data</Attribute>
</RtlPorts>
<RtlPorts>
<name>p_ZZ10top_kernelPA256_K8ap_fixedILi24ELi8EL9ap_q_mode0EL9ap_o_mode0ELi0EEPA256_S2_47_address0</name>
<Object>p_ZZ10top_kernelPA256_K8ap_fixedILi24ELi8EL9ap_q_mode0EL9ap_o_mode0ELi0EEPA256_S2_47</Object>
<Type>array</Type>
<Scope>global</Scope>
<IOProtocol>ap_memory</IOProtocol>
<IOConfig></IOConfig>
<Dir>out</Dir>
<Bits>11</Bits>
<Attribute>address</Attribute>
</RtlPorts>
<RtlPorts>
<name>p_ZZ10top_kernelPA256_K8ap_fixedILi24ELi8EL9ap_q_mode0EL9ap_o_mode0ELi0EEPA256_S2_47_ce0</name>
<Object>p_ZZ10top_kernelPA256_K8ap_fixedILi24ELi8EL9ap_q_mode0EL9ap_o_mode0ELi0EEPA256_S2_47</Object>
<Type>array</Type>
<Scope>global</Scope>
<IOProtocol>ap_memory</IOProtocol>
<IOConfig></IOConfig>
<Dir>out</Dir>
<Bits>1</Bits>
<Attribute>control</Attribute>
</RtlPorts>
<RtlPorts>
<name>p_ZZ10top_kernelPA256_K8ap_fixedILi24ELi8EL9ap_q_mode0EL9ap_o_mode0ELi0EEPA256_S2_47_q0</name>
<Object>p_ZZ10top_kernelPA256_K8ap_fixedILi24ELi8EL9ap_q_mode0EL9ap_o_mode0ELi0EEPA256_S2_47</Object>
<Type>array</Type>
<Scope>global</Scope>
<IOProtocol>ap_memory</IOProtocol>
<IOConfig></IOConfig>
<Dir>in</Dir>
<Bits>24</Bits>
<Attribute>data</Attribute>
</RtlPorts>
<RtlPorts>
<name>p_ZZ10top_kernelPA256_K8ap_fixedILi24ELi8EL9ap_q_mode0EL9ap_o_mode0ELi0EEPA256_S2_46_address0</name>
<Object>p_ZZ10top_kernelPA256_K8ap_fixedILi24ELi8EL9ap_q_mode0EL9ap_o_mode0ELi0EEPA256_S2_46</Object>
<Type>array</Type>
<Scope>global</Scope>
<IOProtocol>ap_memory</IOProtocol>
<IOConfig></IOConfig>
<Dir>out</Dir>
<Bits>11</Bits>
<Attribute>address</Attribute>
</RtlPorts>
<RtlPorts>
<name>p_ZZ10top_kernelPA256_K8ap_fixedILi24ELi8EL9ap_q_mode0EL9ap_o_mode0ELi0EEPA256_S2_46_ce0</name>
<Object>p_ZZ10top_kernelPA256_K8ap_fixedILi24ELi8EL9ap_q_mode0EL9ap_o_mode0ELi0EEPA256_S2_46</Object>
<Type>array</Type>
<Scope>global</Scope>
<IOProtocol>ap_memory</IOProtocol>
<IOConfig></IOConfig>
<Dir>out</Dir>
<Bits>1</Bits>
<Attribute>control</Attribute>
</RtlPorts>
<RtlPorts>
<name>p_ZZ10top_kernelPA256_K8ap_fixedILi24ELi8EL9ap_q_mode0EL9ap_o_mode0ELi0EEPA256_S2_46_q0</name>
<Object>p_ZZ10top_kernelPA256_K8ap_fixedILi24ELi8EL9ap_q_mode0EL9ap_o_mode0ELi0EEPA256_S2_46</Object>
<Type>array</Type>
<Scope>global</Scope>
<IOProtocol>ap_memory</IOProtocol>
<IOConfig></IOConfig>
<Dir>in</Dir>
<Bits>24</Bits>
<Attribute>data</Attribute>
</RtlPorts>
<RtlPorts>
<name>p_ZZ10top_kernelPA256_K8ap_fixedILi24ELi8EL9ap_q_mode0EL9ap_o_mode0ELi0EEPA256_S2_45_address0</name>
<Object>p_ZZ10top_kernelPA256_K8ap_fixedILi24ELi8EL9ap_q_mode0EL9ap_o_mode0ELi0EEPA256_S2_45</Object>
<Type>array</Type>
<Scope>global</Scope>
<IOProtocol>ap_memory</IOProtocol>
<IOConfig></IOConfig>
<Dir>out</Dir>
<Bits>11</Bits>
<Attribute>address</Attribute>
</RtlPorts>
<RtlPorts>
<name>p_ZZ10top_kernelPA256_K8ap_fixedILi24ELi8EL9ap_q_mode0EL9ap_o_mode0ELi0EEPA256_S2_45_ce0</name>
<Object>p_ZZ10top_kernelPA256_K8ap_fixedILi24ELi8EL9ap_q_mode0EL9ap_o_mode0ELi0EEPA256_S2_45</Object>
<Type>array</Type>
<Scope>global</Scope>
<IOProtocol>ap_memory</IOProtocol>
<IOConfig></IOConfig>
<Dir>out</Dir>
<Bits>1</Bits>
<Attribute>control</Attribute>
</RtlPorts>
<RtlPorts>
<name>p_ZZ10top_kernelPA256_K8ap_fixedILi24ELi8EL9ap_q_mode0EL9ap_o_mode0ELi0EEPA256_S2_45_q0</name>
<Object>p_ZZ10top_kernelPA256_K8ap_fixedILi24ELi8EL9ap_q_mode0EL9ap_o_mode0ELi0EEPA256_S2_45</Object>
<Type>array</Type>
<Scope>global</Scope>
<IOProtocol>ap_memory</IOProtocol>
<IOConfig></IOConfig>
<Dir>in</Dir>
<Bits>24</Bits>
<Attribute>data</Attribute>
</RtlPorts>
<RtlPorts>
<name>p_ZZ10top_kernelPA256_K8ap_fixedILi24ELi8EL9ap_q_mode0EL9ap_o_mode0ELi0EEPA256_S2_86_address0</name>
<Object>p_ZZ10top_kernelPA256_K8ap_fixedILi24ELi8EL9ap_q_mode0EL9ap_o_mode0ELi0EEPA256_S2_86</Object>
<Type>array</Type>
<Scope>global</Scope>
<IOProtocol>ap_memory</IOProtocol>
<IOConfig></IOConfig>
<Dir>out</Dir>
<Bits>11</Bits>
<Attribute>address</Attribute>
</RtlPorts>
<RtlPorts>
<name>p_ZZ10top_kernelPA256_K8ap_fixedILi24ELi8EL9ap_q_mode0EL9ap_o_mode0ELi0EEPA256_S2_86_ce0</name>
<Object>p_ZZ10top_kernelPA256_K8ap_fixedILi24ELi8EL9ap_q_mode0EL9ap_o_mode0ELi0EEPA256_S2_86</Object>
<Type>array</Type>
<Scope>global</Scope>
<IOProtocol>ap_memory</IOProtocol>
<IOConfig></IOConfig>
<Dir>out</Dir>
<Bits>1</Bits>
<Attribute>control</Attribute>
</RtlPorts>
<RtlPorts>
<name>p_ZZ10top_kernelPA256_K8ap_fixedILi24ELi8EL9ap_q_mode0EL9ap_o_mode0ELi0EEPA256_S2_86_q0</name>
<Object>p_ZZ10top_kernelPA256_K8ap_fixedILi24ELi8EL9ap_q_mode0EL9ap_o_mode0ELi0EEPA256_S2_86</Object>
<Type>array</Type>
<Scope>global</Scope>
<IOProtocol>ap_memory</IOProtocol>
<IOConfig></IOConfig>
<Dir>in</Dir>
<Bits>24</Bits>
<Attribute>data</Attribute>
</RtlPorts>
<RtlPorts>
<name>p_ZZ10top_kernelPA256_K8ap_fixedILi24ELi8EL9ap_q_mode0EL9ap_o_mode0ELi0EEPA256_S2_85_address0</name>
<Object>p_ZZ10top_kernelPA256_K8ap_fixedILi24ELi8EL9ap_q_mode0EL9ap_o_mode0ELi0EEPA256_S2_85</Object>
<Type>array</Type>
<Scope>global</Scope>
<IOProtocol>ap_memory</IOProtocol>
<IOConfig></IOConfig>
<Dir>out</Dir>
<Bits>11</Bits>
<Attribute>address</Attribute>
</RtlPorts>
<RtlPorts>
<name>p_ZZ10top_kernelPA256_K8ap_fixedILi24ELi8EL9ap_q_mode0EL9ap_o_mode0ELi0EEPA256_S2_85_ce0</name>
<Object>p_ZZ10top_kernelPA256_K8ap_fixedILi24ELi8EL9ap_q_mode0EL9ap_o_mode0ELi0EEPA256_S2_85</Object>
<Type>array</Type>
<Scope>global</Scope>
<IOProtocol>ap_memory</IOProtocol>
<IOConfig></IOConfig>
<Dir>out</Dir>
<Bits>1</Bits>
<Attribute>control</Attribute>
</RtlPorts>
<RtlPorts>
<name>p_ZZ10top_kernelPA256_K8ap_fixedILi24ELi8EL9ap_q_mode0EL9ap_o_mode0ELi0EEPA256_S2_85_q0</name>
<Object>p_ZZ10top_kernelPA256_K8ap_fixedILi24ELi8EL9ap_q_mode0EL9ap_o_mode0ELi0EEPA256_S2_85</Object>
<Type>array</Type>
<Scope>global</Scope>
<IOProtocol>ap_memory</IOProtocol>
<IOConfig></IOConfig>
<Dir>in</Dir>
<Bits>24</Bits>
<Attribute>data</Attribute>
</RtlPorts>
<RtlPorts>
<name>p_ZZ10top_kernelPA256_K8ap_fixedILi24ELi8EL9ap_q_mode0EL9ap_o_mode0ELi0EEPA256_S2_84_address0</name>
<Object>p_ZZ10top_kernelPA256_K8ap_fixedILi24ELi8EL9ap_q_mode0EL9ap_o_mode0ELi0EEPA256_S2_84</Object>
<Type>array</Type>
<Scope>global</Scope>
<IOProtocol>ap_memory</IOProtocol>
<IOConfig></IOConfig>
<Dir>out</Dir>
<Bits>11</Bits>
<Attribute>address</Attribute>
</RtlPorts>
<RtlPorts>
<name>p_ZZ10top_kernelPA256_K8ap_fixedILi24ELi8EL9ap_q_mode0EL9ap_o_mode0ELi0EEPA256_S2_84_ce0</name>
<Object>p_ZZ10top_kernelPA256_K8ap_fixedILi24ELi8EL9ap_q_mode0EL9ap_o_mode0ELi0EEPA256_S2_84</Object>
<Type>array</Type>
<Scope>global</Scope>
<IOProtocol>ap_memory</IOProtocol>
<IOConfig></IOConfig>
<Dir>out</Dir>
<Bits>1</Bits>
<Attribute>control</Attribute>
</RtlPorts>
<RtlPorts>
<name>p_ZZ10top_kernelPA256_K8ap_fixedILi24ELi8EL9ap_q_mode0EL9ap_o_mode0ELi0EEPA256_S2_84_q0</name>
<Object>p_ZZ10top_kernelPA256_K8ap_fixedILi24ELi8EL9ap_q_mode0EL9ap_o_mode0ELi0EEPA256_S2_84</Object>
<Type>array</Type>
<Scope>global</Scope>
<IOProtocol>ap_memory</IOProtocol>
<IOConfig></IOConfig>
<Dir>in</Dir>
<Bits>24</Bits>
<Attribute>data</Attribute>
</RtlPorts>
<RtlPorts>
<name>p_ZZ10top_kernelPA256_K8ap_fixedILi24ELi8EL9ap_q_mode0EL9ap_o_mode0ELi0EEPA256_S2_83_address0</name>
<Object>p_ZZ10top_kernelPA256_K8ap_fixedILi24ELi8EL9ap_q_mode0EL9ap_o_mode0ELi0EEPA256_S2_83</Object>
<Type>array</Type>
<Scope>global</Scope>
<IOProtocol>ap_memory</IOProtocol>
<IOConfig></IOConfig>
<Dir>out</Dir>
<Bits>11</Bits>
<Attribute>address</Attribute>
</RtlPorts>
<RtlPorts>
<name>p_ZZ10top_kernelPA256_K8ap_fixedILi24ELi8EL9ap_q_mode0EL9ap_o_mode0ELi0EEPA256_S2_83_ce0</name>
<Object>p_ZZ10top_kernelPA256_K8ap_fixedILi24ELi8EL9ap_q_mode0EL9ap_o_mode0ELi0EEPA256_S2_83</Object>
<Type>array</Type>
<Scope>global</Scope>
<IOProtocol>ap_memory</IOProtocol>
<IOConfig></IOConfig>
<Dir>out</Dir>
<Bits>1</Bits>
<Attribute>control</Attribute>
</RtlPorts>
<RtlPorts>
<name>p_ZZ10top_kernelPA256_K8ap_fixedILi24ELi8EL9ap_q_mode0EL9ap_o_mode0ELi0EEPA256_S2_83_q0</name>
<Object>p_ZZ10top_kernelPA256_K8ap_fixedILi24ELi8EL9ap_q_mode0EL9ap_o_mode0ELi0EEPA256_S2_83</Object>
<Type>array</Type>
<Scope>global</Scope>
<IOProtocol>ap_memory</IOProtocol>
<IOConfig></IOConfig>
<Dir>in</Dir>
<Bits>24</Bits>
<Attribute>data</Attribute>
</RtlPorts>
<RtlPorts>
<name>p_ZZ10top_kernelPA256_K8ap_fixedILi24ELi8EL9ap_q_mode0EL9ap_o_mode0ELi0EEPA256_S2_82_address0</name>
<Object>p_ZZ10top_kernelPA256_K8ap_fixedILi24ELi8EL9ap_q_mode0EL9ap_o_mode0ELi0EEPA256_S2_82</Object>
<Type>array</Type>
<Scope>global</Scope>
<IOProtocol>ap_memory</IOProtocol>
<IOConfig></IOConfig>
<Dir>out</Dir>
<Bits>11</Bits>
<Attribute>address</Attribute>
</RtlPorts>
<RtlPorts>
<name>p_ZZ10top_kernelPA256_K8ap_fixedILi24ELi8EL9ap_q_mode0EL9ap_o_mode0ELi0EEPA256_S2_82_ce0</name>
<Object>p_ZZ10top_kernelPA256_K8ap_fixedILi24ELi8EL9ap_q_mode0EL9ap_o_mode0ELi0EEPA256_S2_82</Object>
<Type>array</Type>
<Scope>global</Scope>
<IOProtocol>ap_memory</IOProtocol>
<IOConfig></IOConfig>
<Dir>out</Dir>
<Bits>1</Bits>
<Attribute>control</Attribute>
</RtlPorts>
<RtlPorts>
<name>p_ZZ10top_kernelPA256_K8ap_fixedILi24ELi8EL9ap_q_mode0EL9ap_o_mode0ELi0EEPA256_S2_82_q0</name>
<Object>p_ZZ10top_kernelPA256_K8ap_fixedILi24ELi8EL9ap_q_mode0EL9ap_o_mode0ELi0EEPA256_S2_82</Object>
<Type>array</Type>
<Scope>global</Scope>
<IOProtocol>ap_memory</IOProtocol>
<IOConfig></IOConfig>
<Dir>in</Dir>
<Bits>24</Bits>
<Attribute>data</Attribute>
</RtlPorts>
<RtlPorts>
<name>p_ZZ10top_kernelPA256_K8ap_fixedILi24ELi8EL9ap_q_mode0EL9ap_o_mode0ELi0EEPA256_S2_81_address0</name>
<Object>p_ZZ10top_kernelPA256_K8ap_fixedILi24ELi8EL9ap_q_mode0EL9ap_o_mode0ELi0EEPA256_S2_81</Object>
<Type>array</Type>
<Scope>global</Scope>
<IOProtocol>ap_memory</IOProtocol>
<IOConfig></IOConfig>
<Dir>out</Dir>
<Bits>11</Bits>
<Attribute>address</Attribute>
</RtlPorts>
<RtlPorts>
<name>p_ZZ10top_kernelPA256_K8ap_fixedILi24ELi8EL9ap_q_mode0EL9ap_o_mode0ELi0EEPA256_S2_81_ce0</name>
<Object>p_ZZ10top_kernelPA256_K8ap_fixedILi24ELi8EL9ap_q_mode0EL9ap_o_mode0ELi0EEPA256_S2_81</Object>
<Type>array</Type>
<Scope>global</Scope>
<IOProtocol>ap_memory</IOProtocol>
<IOConfig></IOConfig>
<Dir>out</Dir>
<Bits>1</Bits>
<Attribute>control</Attribute>
</RtlPorts>
<RtlPorts>
<name>p_ZZ10top_kernelPA256_K8ap_fixedILi24ELi8EL9ap_q_mode0EL9ap_o_mode0ELi0EEPA256_S2_81_q0</name>
<Object>p_ZZ10top_kernelPA256_K8ap_fixedILi24ELi8EL9ap_q_mode0EL9ap_o_mode0ELi0EEPA256_S2_81</Object>
<Type>array</Type>
<Scope>global</Scope>
<IOProtocol>ap_memory</IOProtocol>
<IOConfig></IOConfig>
<Dir>in</Dir>
<Bits>24</Bits>
<Attribute>data</Attribute>
</RtlPorts>
<RtlPorts>
<name>top_kernel_ap_fixed_const_256_ap_fixed_24_8_0_0_0_256_mem_A_2_address0</name>
<Object>top_kernel_ap_fixed_const_256_ap_fixed_24_8_0_0_0_256_mem_A_2</Object>
<Type>array</Type>
<Scope>global</Scope>
<IOProtocol>ap_memory</IOProtocol>
<IOConfig></IOConfig>
<Dir>out</Dir>
<Bits>11</Bits>
<Attribute>address</Attribute>
</RtlPorts>
<RtlPorts>
<name>top_kernel_ap_fixed_const_256_ap_fixed_24_8_0_0_0_256_mem_A_2_ce0</name>
<Object>top_kernel_ap_fixed_const_256_ap_fixed_24_8_0_0_0_256_mem_A_2</Object>
<Type>array</Type>
<Scope>global</Scope>
<IOProtocol>ap_memory</IOProtocol>
<IOConfig></IOConfig>
<Dir>out</Dir>
<Bits>1</Bits>
<Attribute>control</Attribute>
</RtlPorts>
<RtlPorts>
<name>top_kernel_ap_fixed_const_256_ap_fixed_24_8_0_0_0_256_mem_A_2_q0</name>
<Object>top_kernel_ap_fixed_const_256_ap_fixed_24_8_0_0_0_256_mem_A_2</Object>
<Type>array</Type>
<Scope>global</Scope>
<IOProtocol>ap_memory</IOProtocol>
<IOConfig></IOConfig>
<Dir>in</Dir>
<Bits>24</Bits>
<Attribute>data</Attribute>
</RtlPorts>
<RtlPorts>
<name>top_kernel_ap_fixed_const_256_ap_fixed_24_8_0_0_0_256_mem_A_1_address0</name>
<Object>top_kernel_ap_fixed_const_256_ap_fixed_24_8_0_0_0_256_mem_A_1</Object>
<Type>array</Type>
<Scope>global</Scope>
<IOProtocol>ap_memory</IOProtocol>
<IOConfig></IOConfig>
<Dir>out</Dir>
<Bits>11</Bits>
<Attribute>address</Attribute>
</RtlPorts>
<RtlPorts>
<name>top_kernel_ap_fixed_const_256_ap_fixed_24_8_0_0_0_256_mem_A_1_ce0</name>
<Object>top_kernel_ap_fixed_const_256_ap_fixed_24_8_0_0_0_256_mem_A_1</Object>
<Type>array</Type>
<Scope>global</Scope>
<IOProtocol>ap_memory</IOProtocol>
<IOConfig></IOConfig>
<Dir>out</Dir>
<Bits>1</Bits>
<Attribute>control</Attribute>
</RtlPorts>
<RtlPorts>
<name>top_kernel_ap_fixed_const_256_ap_fixed_24_8_0_0_0_256_mem_A_1_q0</name>
<Object>top_kernel_ap_fixed_const_256_ap_fixed_24_8_0_0_0_256_mem_A_1</Object>
<Type>array</Type>
<Scope>global</Scope>
<IOProtocol>ap_memory</IOProtocol>
<IOConfig></IOConfig>
<Dir>in</Dir>
<Bits>24</Bits>
<Attribute>data</Attribute>
</RtlPorts>
<RtlPorts>
<name>top_kernel_ap_fixed_const_256_ap_fixed_24_8_0_0_0_256_mem_A_address0</name>
<Object>top_kernel_ap_fixed_const_256_ap_fixed_24_8_0_0_0_256_mem_A</Object>
<Type>array</Type>
<Scope>global</Scope>
<IOProtocol>ap_memory</IOProtocol>
<IOConfig></IOConfig>
<Dir>out</Dir>
<Bits>11</Bits>
<Attribute>address</Attribute>
</RtlPorts>
<RtlPorts>
<name>top_kernel_ap_fixed_const_256_ap_fixed_24_8_0_0_0_256_mem_A_ce0</name>
<Object>top_kernel_ap_fixed_const_256_ap_fixed_24_8_0_0_0_256_mem_A</Object>
<Type>array</Type>
<Scope>global</Scope>
<IOProtocol>ap_memory</IOProtocol>
<IOConfig></IOConfig>
<Dir>out</Dir>
<Bits>1</Bits>
<Attribute>control</Attribute>
</RtlPorts>
<RtlPorts>
<name>top_kernel_ap_fixed_const_256_ap_fixed_24_8_0_0_0_256_mem_A_q0</name>
<Object>top_kernel_ap_fixed_const_256_ap_fixed_24_8_0_0_0_256_mem_A</Object>
<Type>array</Type>
<Scope>global</Scope>
<IOProtocol>ap_memory</IOProtocol>
<IOConfig></IOConfig>
<Dir>in</Dir>
<Bits>24</Bits>
<Attribute>data</Attribute>
</RtlPorts>
<RtlPorts>
<name>p_ZZ10top_kernelPA256_K8ap_fixedILi24ELi8EL9ap_q_mode0EL9ap_o_mode0ELi0EEPA256_S2_80_address0</name>
<Object>p_ZZ10top_kernelPA256_K8ap_fixedILi24ELi8EL9ap_q_mode0EL9ap_o_mode0ELi0EEPA256_S2_80</Object>
<Type>array</Type>
<Scope>global</Scope>
<IOProtocol>ap_memory</IOProtocol>
<IOConfig></IOConfig>
<Dir>out</Dir>
<Bits>11</Bits>
<Attribute>address</Attribute>
</RtlPorts>
<RtlPorts>
<name>p_ZZ10top_kernelPA256_K8ap_fixedILi24ELi8EL9ap_q_mode0EL9ap_o_mode0ELi0EEPA256_S2_80_ce0</name>
<Object>p_ZZ10top_kernelPA256_K8ap_fixedILi24ELi8EL9ap_q_mode0EL9ap_o_mode0ELi0EEPA256_S2_80</Object>
<Type>array</Type>
<Scope>global</Scope>
<IOProtocol>ap_memory</IOProtocol>
<IOConfig></IOConfig>
<Dir>out</Dir>
<Bits>1</Bits>
<Attribute>control</Attribute>
</RtlPorts>
<RtlPorts>
<name>p_ZZ10top_kernelPA256_K8ap_fixedILi24ELi8EL9ap_q_mode0EL9ap_o_mode0ELi0EEPA256_S2_80_q0</name>
<Object>p_ZZ10top_kernelPA256_K8ap_fixedILi24ELi8EL9ap_q_mode0EL9ap_o_mode0ELi0EEPA256_S2_80</Object>
<Type>array</Type>
<Scope>global</Scope>
<IOProtocol>ap_memory</IOProtocol>
<IOConfig></IOConfig>
<Dir>in</Dir>
<Bits>24</Bits>
<Attribute>data</Attribute>
</RtlPorts>
<RtlPorts>
<name>p_ZZ10top_kernelPA256_K8ap_fixedILi24ELi8EL9ap_q_mode0EL9ap_o_mode0ELi0EEPA256_S2_79_address0</name>
<Object>p_ZZ10top_kernelPA256_K8ap_fixedILi24ELi8EL9ap_q_mode0EL9ap_o_mode0ELi0EEPA256_S2_79</Object>
<Type>array</Type>
<Scope>global</Scope>
<IOProtocol>ap_memory</IOProtocol>
<IOConfig></IOConfig>
<Dir>out</Dir>
<Bits>11</Bits>
<Attribute>address</Attribute>
</RtlPorts>
<RtlPorts>
<name>p_ZZ10top_kernelPA256_K8ap_fixedILi24ELi8EL9ap_q_mode0EL9ap_o_mode0ELi0EEPA256_S2_79_ce0</name>
<Object>p_ZZ10top_kernelPA256_K8ap_fixedILi24ELi8EL9ap_q_mode0EL9ap_o_mode0ELi0EEPA256_S2_79</Object>
<Type>array</Type>
<Scope>global</Scope>
<IOProtocol>ap_memory</IOProtocol>
<IOConfig></IOConfig>
<Dir>out</Dir>
<Bits>1</Bits>
<Attribute>control</Attribute>
</RtlPorts>
<RtlPorts>
<name>p_ZZ10top_kernelPA256_K8ap_fixedILi24ELi8EL9ap_q_mode0EL9ap_o_mode0ELi0EEPA256_S2_79_q0</name>
<Object>p_ZZ10top_kernelPA256_K8ap_fixedILi24ELi8EL9ap_q_mode0EL9ap_o_mode0ELi0EEPA256_S2_79</Object>
<Type>array</Type>
<Scope>global</Scope>
<IOProtocol>ap_memory</IOProtocol>
<IOConfig></IOConfig>
<Dir>in</Dir>
<Bits>24</Bits>
<Attribute>data</Attribute>
</RtlPorts>
<RtlPorts>
<name>p_ZZ10top_kernelPA256_K8ap_fixedILi24ELi8EL9ap_q_mode0EL9ap_o_mode0ELi0EEPA256_S2_78_address0</name>
<Object>p_ZZ10top_kernelPA256_K8ap_fixedILi24ELi8EL9ap_q_mode0EL9ap_o_mode0ELi0EEPA256_S2_78</Object>
<Type>array</Type>
<Scope>global</Scope>
<IOProtocol>ap_memory</IOProtocol>
<IOConfig></IOConfig>
<Dir>out</Dir>
<Bits>11</Bits>
<Attribute>address</Attribute>
</RtlPorts>
<RtlPorts>
<name>p_ZZ10top_kernelPA256_K8ap_fixedILi24ELi8EL9ap_q_mode0EL9ap_o_mode0ELi0EEPA256_S2_78_ce0</name>
<Object>p_ZZ10top_kernelPA256_K8ap_fixedILi24ELi8EL9ap_q_mode0EL9ap_o_mode0ELi0EEPA256_S2_78</Object>
<Type>array</Type>
<Scope>global</Scope>
<IOProtocol>ap_memory</IOProtocol>
<IOConfig></IOConfig>
<Dir>out</Dir>
<Bits>1</Bits>
<Attribute>control</Attribute>
</RtlPorts>
<RtlPorts>
<name>p_ZZ10top_kernelPA256_K8ap_fixedILi24ELi8EL9ap_q_mode0EL9ap_o_mode0ELi0EEPA256_S2_78_q0</name>
<Object>p_ZZ10top_kernelPA256_K8ap_fixedILi24ELi8EL9ap_q_mode0EL9ap_o_mode0ELi0EEPA256_S2_78</Object>
<Type>array</Type>
<Scope>global</Scope>
<IOProtocol>ap_memory</IOProtocol>
<IOConfig></IOConfig>
<Dir>in</Dir>
<Bits>24</Bits>
<Attribute>data</Attribute>
</RtlPorts>
<RtlPorts>
<name>p_ZZ10top_kernelPA256_K8ap_fixedILi24ELi8EL9ap_q_mode0EL9ap_o_mode0ELi0EEPA256_S2_77_address0</name>
<Object>p_ZZ10top_kernelPA256_K8ap_fixedILi24ELi8EL9ap_q_mode0EL9ap_o_mode0ELi0EEPA256_S2_77</Object>
<Type>array</Type>
<Scope>global</Scope>
<IOProtocol>ap_memory</IOProtocol>
<IOConfig></IOConfig>
<Dir>out</Dir>
<Bits>11</Bits>
<Attribute>address</Attribute>
</RtlPorts>
<RtlPorts>
<name>p_ZZ10top_kernelPA256_K8ap_fixedILi24ELi8EL9ap_q_mode0EL9ap_o_mode0ELi0EEPA256_S2_77_ce0</name>
<Object>p_ZZ10top_kernelPA256_K8ap_fixedILi24ELi8EL9ap_q_mode0EL9ap_o_mode0ELi0EEPA256_S2_77</Object>
<Type>array</Type>
<Scope>global</Scope>
<IOProtocol>ap_memory</IOProtocol>
<IOConfig></IOConfig>
<Dir>out</Dir>
<Bits>1</Bits>
<Attribute>control</Attribute>
</RtlPorts>
<RtlPorts>
<name>p_ZZ10top_kernelPA256_K8ap_fixedILi24ELi8EL9ap_q_mode0EL9ap_o_mode0ELi0EEPA256_S2_77_q0</name>
<Object>p_ZZ10top_kernelPA256_K8ap_fixedILi24ELi8EL9ap_q_mode0EL9ap_o_mode0ELi0EEPA256_S2_77</Object>
<Type>array</Type>
<Scope>global</Scope>
<IOProtocol>ap_memory</IOProtocol>
<IOConfig></IOConfig>
<Dir>in</Dir>
<Bits>24</Bits>
<Attribute>data</Attribute>
</RtlPorts>
<RtlPorts>
<name>p_ZZ10top_kernelPA256_K8ap_fixedILi24ELi8EL9ap_q_mode0EL9ap_o_mode0ELi0EEPA256_S2_76_address0</name>
<Object>p_ZZ10top_kernelPA256_K8ap_fixedILi24ELi8EL9ap_q_mode0EL9ap_o_mode0ELi0EEPA256_S2_76</Object>
<Type>array</Type>
<Scope>global</Scope>
<IOProtocol>ap_memory</IOProtocol>
<IOConfig></IOConfig>
<Dir>out</Dir>
<Bits>11</Bits>
<Attribute>address</Attribute>
</RtlPorts>
<RtlPorts>
<name>p_ZZ10top_kernelPA256_K8ap_fixedILi24ELi8EL9ap_q_mode0EL9ap_o_mode0ELi0EEPA256_S2_76_ce0</name>
<Object>p_ZZ10top_kernelPA256_K8ap_fixedILi24ELi8EL9ap_q_mode0EL9ap_o_mode0ELi0EEPA256_S2_76</Object>
<Type>array</Type>
<Scope>global</Scope>
<IOProtocol>ap_memory</IOProtocol>
<IOConfig></IOConfig>
<Dir>out</Dir>
<Bits>1</Bits>
<Attribute>control</Attribute>
</RtlPorts>
<RtlPorts>
<name>p_ZZ10top_kernelPA256_K8ap_fixedILi24ELi8EL9ap_q_mode0EL9ap_o_mode0ELi0EEPA256_S2_76_q0</name>
<Object>p_ZZ10top_kernelPA256_K8ap_fixedILi24ELi8EL9ap_q_mode0EL9ap_o_mode0ELi0EEPA256_S2_76</Object>
<Type>array</Type>
<Scope>global</Scope>
<IOProtocol>ap_memory</IOProtocol>
<IOConfig></IOConfig>
<Dir>in</Dir>
<Bits>24</Bits>
<Attribute>data</Attribute>
</RtlPorts>
<RtlPorts>
<name>p_ZZ10top_kernelPA256_K8ap_fixedILi24ELi8EL9ap_q_mode0EL9ap_o_mode0ELi0EEPA256_S2_75_address0</name>
<Object>p_ZZ10top_kernelPA256_K8ap_fixedILi24ELi8EL9ap_q_mode0EL9ap_o_mode0ELi0EEPA256_S2_75</Object>
<Type>array</Type>
<Scope>global</Scope>
<IOProtocol>ap_memory</IOProtocol>
<IOConfig></IOConfig>
<Dir>out</Dir>
<Bits>11</Bits>
<Attribute>address</Attribute>
</RtlPorts>
<RtlPorts>
<name>p_ZZ10top_kernelPA256_K8ap_fixedILi24ELi8EL9ap_q_mode0EL9ap_o_mode0ELi0EEPA256_S2_75_ce0</name>
<Object>p_ZZ10top_kernelPA256_K8ap_fixedILi24ELi8EL9ap_q_mode0EL9ap_o_mode0ELi0EEPA256_S2_75</Object>
<Type>array</Type>
<Scope>global</Scope>
<IOProtocol>ap_memory</IOProtocol>
<IOConfig></IOConfig>
<Dir>out</Dir>
<Bits>1</Bits>
<Attribute>control</Attribute>
</RtlPorts>
<RtlPorts>
<name>p_ZZ10top_kernelPA256_K8ap_fixedILi24ELi8EL9ap_q_mode0EL9ap_o_mode0ELi0EEPA256_S2_75_q0</name>
<Object>p_ZZ10top_kernelPA256_K8ap_fixedILi24ELi8EL9ap_q_mode0EL9ap_o_mode0ELi0EEPA256_S2_75</Object>
<Type>array</Type>
<Scope>global</Scope>
<IOProtocol>ap_memory</IOProtocol>
<IOConfig></IOConfig>
<Dir>in</Dir>
<Bits>24</Bits>
<Attribute>data</Attribute>
</RtlPorts>
<RtlPorts>
<name>p_ZZ10top_kernelPA256_K8ap_fixedILi24ELi8EL9ap_q_mode0EL9ap_o_mode0ELi0EEPA256_S2_74_address0</name>
<Object>p_ZZ10top_kernelPA256_K8ap_fixedILi24ELi8EL9ap_q_mode0EL9ap_o_mode0ELi0EEPA256_S2_74</Object>
<Type>array</Type>
<Scope>global</Scope>
<IOProtocol>ap_memory</IOProtocol>
<IOConfig></IOConfig>
<Dir>out</Dir>
<Bits>11</Bits>
<Attribute>address</Attribute>
</RtlPorts>
<RtlPorts>
<name>p_ZZ10top_kernelPA256_K8ap_fixedILi24ELi8EL9ap_q_mode0EL9ap_o_mode0ELi0EEPA256_S2_74_ce0</name>
<Object>p_ZZ10top_kernelPA256_K8ap_fixedILi24ELi8EL9ap_q_mode0EL9ap_o_mode0ELi0EEPA256_S2_74</Object>
<Type>array</Type>
<Scope>global</Scope>
<IOProtocol>ap_memory</IOProtocol>
<IOConfig></IOConfig>
<Dir>out</Dir>
<Bits>1</Bits>
<Attribute>control</Attribute>
</RtlPorts>
<RtlPorts>
<name>p_ZZ10top_kernelPA256_K8ap_fixedILi24ELi8EL9ap_q_mode0EL9ap_o_mode0ELi0EEPA256_S2_74_q0</name>
<Object>p_ZZ10top_kernelPA256_K8ap_fixedILi24ELi8EL9ap_q_mode0EL9ap_o_mode0ELi0EEPA256_S2_74</Object>
<Type>array</Type>
<Scope>global</Scope>
<IOProtocol>ap_memory</IOProtocol>
<IOConfig></IOConfig>
<Dir>in</Dir>
<Bits>24</Bits>
<Attribute>data</Attribute>
</RtlPorts>
<RtlPorts>
<name>p_ZZ10top_kernelPA256_K8ap_fixedILi24ELi8EL9ap_q_mode0EL9ap_o_mode0ELi0EEPA256_S2_73_address0</name>
<Object>p_ZZ10top_kernelPA256_K8ap_fixedILi24ELi8EL9ap_q_mode0EL9ap_o_mode0ELi0EEPA256_S2_73</Object>
<Type>array</Type>
<Scope>global</Scope>
<IOProtocol>ap_memory</IOProtocol>
<IOConfig></IOConfig>
<Dir>out</Dir>
<Bits>11</Bits>
<Attribute>address</Attribute>
</RtlPorts>
<RtlPorts>
<name>p_ZZ10top_kernelPA256_K8ap_fixedILi24ELi8EL9ap_q_mode0EL9ap_o_mode0ELi0EEPA256_S2_73_ce0</name>
<Object>p_ZZ10top_kernelPA256_K8ap_fixedILi24ELi8EL9ap_q_mode0EL9ap_o_mode0ELi0EEPA256_S2_73</Object>
<Type>array</Type>
<Scope>global</Scope>
<IOProtocol>ap_memory</IOProtocol>
<IOConfig></IOConfig>
<Dir>out</Dir>
<Bits>1</Bits>
<Attribute>control</Attribute>
</RtlPorts>
<RtlPorts>
<name>p_ZZ10top_kernelPA256_K8ap_fixedILi24ELi8EL9ap_q_mode0EL9ap_o_mode0ELi0EEPA256_S2_73_q0</name>
<Object>p_ZZ10top_kernelPA256_K8ap_fixedILi24ELi8EL9ap_q_mode0EL9ap_o_mode0ELi0EEPA256_S2_73</Object>
<Type>array</Type>
<Scope>global</Scope>
<IOProtocol>ap_memory</IOProtocol>
<IOConfig></IOConfig>
<Dir>in</Dir>
<Bits>24</Bits>
<Attribute>data</Attribute>
</RtlPorts>
<RtlPorts>
<name>p_ZZ10top_kernelPA256_K8ap_fixedILi24ELi8EL9ap_q_mode0EL9ap_o_mode0ELi0EEPA256_S2_72_address0</name>
<Object>p_ZZ10top_kernelPA256_K8ap_fixedILi24ELi8EL9ap_q_mode0EL9ap_o_mode0ELi0EEPA256_S2_72</Object>
<Type>array</Type>
<Scope>global</Scope>
<IOProtocol>ap_memory</IOProtocol>
<IOConfig></IOConfig>
<Dir>out</Dir>
<Bits>11</Bits>
<Attribute>address</Attribute>
</RtlPorts>
<RtlPorts>
<name>p_ZZ10top_kernelPA256_K8ap_fixedILi24ELi8EL9ap_q_mode0EL9ap_o_mode0ELi0EEPA256_S2_72_ce0</name>
<Object>p_ZZ10top_kernelPA256_K8ap_fixedILi24ELi8EL9ap_q_mode0EL9ap_o_mode0ELi0EEPA256_S2_72</Object>
<Type>array</Type>
<Scope>global</Scope>
<IOProtocol>ap_memory</IOProtocol>
<IOConfig></IOConfig>
<Dir>out</Dir>
<Bits>1</Bits>
<Attribute>control</Attribute>
</RtlPorts>
<RtlPorts>
<name>p_ZZ10top_kernelPA256_K8ap_fixedILi24ELi8EL9ap_q_mode0EL9ap_o_mode0ELi0EEPA256_S2_72_q0</name>
<Object>p_ZZ10top_kernelPA256_K8ap_fixedILi24ELi8EL9ap_q_mode0EL9ap_o_mode0ELi0EEPA256_S2_72</Object>
<Type>array</Type>
<Scope>global</Scope>
<IOProtocol>ap_memory</IOProtocol>
<IOConfig></IOConfig>
<Dir>in</Dir>
<Bits>24</Bits>
<Attribute>data</Attribute>
</RtlPorts>
</InterfaceSummary>

</profile>
